{"pagination": {"limit": 100, "offset": 0, "count": 100, "total": 249365}, "data": [{"flight_date": "2025-07-06", "flight_status": "scheduled", "departure": {"airport": "Tontouta", "timezone": "Pacific/Noumea", "iata": "NOU", "icao": "NWWW", "terminal": null, "gate": null, "delay": null, "scheduled": "2025-07-06T00:55:00+00:00", "estimated": "2025-07-06T00:55:00+00:00", "actual": null, "estimated_runway": null, "actual_runway": null}, "arrival": {"airport": "Singapore Changi", "timezone": "Asia/Singapore", "iata": "SIN", "icao": "WSSS", "terminal": "3", "gate": null, "baggage": null, "scheduled": "2025-07-06T07:15:00+00:00", "delay": null, "estimated": null, "actual": null, "estimated_runway": null, "actual_runway": null}, "airline": {"name": "Hi Fly", "iata": "5K", "icao": "HFY"}, "flight": {"number": "740", "iata": "5K740", "icao": "HFY740", "codeshared": null}, "aircraft": null, "live": null}, {"flight_date": "2025-07-06", "flight_status": "scheduled", "departure": {"airport": "Tontouta", "timezone": "Pacific/Noumea", "iata": "NOU", "icao": "NWWW", "terminal": null, "gate": null, "delay": null, "scheduled": "2025-07-06T00:55:00+00:00", "estimated": "2025-07-06T00:55:00+00:00", "actual": null, "estimated_runway": null, "actual_runway": null}, "arrival": {"airport": "Singapore Changi", "timezone": "Asia/Singapore", "iata": "SIN", "icao": "WSSS", "terminal": "3", "gate": null, "baggage": null, "scheduled": "2025-07-06T07:15:00+00:00", "delay": null, "estimated": null, "actual": null, "estimated_runway": null, "actual_runway": null}, "airline": {"name": "Air France", "iata": "AF", "icao": "AFR"}, "flight": {"number": "4022", "iata": "AF4022", "icao": "AFR4022", "codeshared": {"airline_name": "hi fly", "airline_iata": "5k", "airline_icao": "hfy", "flight_number": "740", "flight_iata": "5k740", "flight_icao": "hfy740"}}, "aircraft": null, "live": null}, {"flight_date": "2025-07-06", "flight_status": "scheduled", "departure": {"airport": "Auckland International", "timezone": "Pacific/Auckland", "iata": "AKL", "icao": "NZAA", "terminal": "I", "gate": null, "delay": null, "scheduled": "2025-07-06T00:25:00+00:00", "estimated": "2025-07-06T00:25:00+00:00", "actual": null, "estimated_runway": null, "actual_runway": null}, "arrival": {"airport": "Kuala Lumpur International Airport (klia)", "timezone": "Asia/Kuala_Lumpur", "iata": "KUL", "icao": "WMKK", "terminal": "1", "gate": null, "baggage": null, "scheduled": "2025-07-06T07:55:00+00:00", "delay": null, "estimated": null, "actual": null, "estimated_runway": null, "actual_runway": null}, "airline": {"name": "Malaysia Airlines", "iata": "MH", "icao": "MAS"}, "flight": {"number": "132", "iata": "MH132", "icao": "MAS132", "codeshared": null}, "aircraft": null, "live": null}, {"flight_date": "2025-07-06", "flight_status": "scheduled", "departure": {"airport": "Auckland International", "timezone": "Pacific/Auckland", "iata": "AKL", "icao": "NZAA", "terminal": "I", "gate": null, "delay": null, "scheduled": "2025-07-06T00:25:00+00:00", "estimated": "2025-07-06T00:25:00+00:00", "actual": null, "estimated_runway": null, "actual_runway": null}, "arrival": {"airport": "Kuala Lumpur International Airport (klia)", "timezone": "Asia/Kuala_Lumpur", "iata": "KUL", "icao": "WMKK", "terminal": "1", "gate": null, "baggage": null, "scheduled": "2025-07-06T07:55:00+00:00", "delay": null, "estimated": null, "actual": null, "estimated_runway": null, "actual_runway": null}, "airline": {"name": "Oman Air", "iata": "WY", "icao": "OMA"}, "flight": {"number": "5585", "iata": "WY5585", "icao": "OMA5585", "codeshared": {"airline_name": "malaysia airlines", "airline_iata": "mh", "airline_icao": "mas", "flight_number": "132", "flight_iata": "mh132", "flight_icao": "mas132"}}, "aircraft": null, "live": null}, {"flight_date": "2025-07-06", "flight_status": "scheduled", "departure": {"airport": "Auckland International", "timezone": "Pacific/Auckland", "iata": "AKL", "icao": "NZAA", "terminal": "I", "gate": null, "delay": null, "scheduled": "2025-07-06T00:25:00+00:00", "estimated": "2025-07-06T00:25:00+00:00", "actual": null, "estimated_runway": null, "actual_runway": null}, "arrival": {"airport": "Kuala Lumpur International Airport (klia)", "timezone": "Asia/Kuala_Lumpur", "iata": "KUL", "icao": "WMKK", "terminal": "1", "gate": null, "baggage": null, "scheduled": "2025-07-06T07:55:00+00:00", "delay": null, "estimated": null, "actual": null, "estimated_runway": null, "actual_runway": null}, "airline": {"name": "SriLankan Airlines", "iata": "UL", "icao": "ALK"}, "flight": {"number": "2120", "iata": "UL2120", "icao": "ALK2120", "codeshared": {"airline_name": "malaysia airlines", "airline_iata": "mh", "airline_icao": "mas", "flight_number": "132", "flight_iata": "mh132", "flight_icao": "mas132"}}, "aircraft": null, "live": null}, {"flight_date": "2025-07-06", "flight_status": "scheduled", "departure": {"airport": "Auckland International", "timezone": "Pacific/Auckland", "iata": "AKL", "icao": "NZAA", "terminal": "I", "gate": null, "delay": null, "scheduled": "2025-07-06T00:25:00+00:00", "estimated": "2025-07-06T00:25:00+00:00", "actual": null, "estimated_runway": null, "actual_runway": null}, "arrival": {"airport": "Kuala Lumpur International Airport (klia)", "timezone": "Asia/Kuala_Lumpur", "iata": "KUL", "icao": "WMKK", "terminal": "1", "gate": null, "baggage": null, "scheduled": "2025-07-06T07:55:00+00:00", "delay": null, "estimated": null, "actual": null, "estimated_runway": null, "actual_runway": null}, "airline": {"name": "Turkish Airlines", "iata": "TK", "icao": "THY"}, "flight": {"number": "4802", "iata": "TK4802", "icao": "THY4802", "codeshared": {"airline_name": "malaysia airlines", "airline_iata": "mh", "airline_icao": "mas", "flight_number": "132", "flight_iata": "mh132", "flight_icao": "mas132"}}, "aircraft": null, "live": null}, {"flight_date": "2025-07-06", "flight_status": "scheduled", "departure": {"airport": "Auckland International", "timezone": "Pacific/Auckland", "iata": "AKL", "icao": "NZAA", "terminal": "I", "gate": null, "delay": null, "scheduled": "2025-07-06T00:25:00+00:00", "estimated": "2025-07-06T00:25:00+00:00", "actual": null, "estimated_runway": null, "actual_runway": null}, "arrival": {"airport": "Kuala Lumpur International Airport (klia)", "timezone": "Asia/Kuala_Lumpur", "iata": "KUL", "icao": "WMKK", "terminal": "1", "gate": null, "baggage": null, "scheduled": "2025-07-06T07:55:00+00:00", "delay": null, "estimated": null, "actual": null, "estimated_runway": null, "actual_runway": null}, "airline": {"name": "Qatar Airways", "iata": "QR", "icao": "QTR"}, "flight": {"number": "4970", "iata": "QR4970", "icao": "QTR4970", "codeshared": {"airline_name": "malaysia airlines", "airline_iata": "mh", "airline_icao": "mas", "flight_number": "132", "flight_iata": "mh132", "flight_icao": "mas132"}}, "aircraft": null, "live": null}, {"flight_date": "2025-07-06", "flight_status": "scheduled", "departure": {"airport": "Auckland International", "timezone": "Pacific/Auckland", "iata": "AKL", "icao": "NZAA", "terminal": "I", "gate": null, "delay": null, "scheduled": "2025-07-06T00:25:00+00:00", "estimated": "2025-07-06T00:25:00+00:00", "actual": null, "estimated_runway": null, "actual_runway": null}, "arrival": {"airport": "Kuala Lumpur International Airport (klia)", "timezone": "Asia/Kuala_Lumpur", "iata": "KUL", "icao": "WMKK", "terminal": "1", "gate": null, "baggage": null, "scheduled": "2025-07-06T07:55:00+00:00", "delay": null, "estimated": null, "actual": null, "estimated_runway": null, "actual_runway": null}, "airline": {"name": "KLM", "iata": "KL", "icao": "KLM"}, "flight": {"number": "4096", "iata": "KL4096", "icao": "KLM4096", "codeshared": {"airline_name": "malaysia airlines", "airline_iata": "mh", "airline_icao": "mas", "flight_number": "132", "flight_iata": "mh132", "flight_icao": "mas132"}}, "aircraft": null, "live": null}, {"flight_date": "2025-07-06", "flight_status": "scheduled", "departure": {"airport": "Auckland International", "timezone": "Pacific/Auckland", "iata": "AKL", "icao": "NZAA", "terminal": "I", "gate": null, "delay": null, "scheduled": "2025-07-06T00:25:00+00:00", "estimated": "2025-07-06T00:25:00+00:00", "actual": null, "estimated_runway": null, "actual_runway": null}, "arrival": {"airport": "Kuala Lumpur International Airport (klia)", "timezone": "Asia/Kuala_Lumpur", "iata": "KUL", "icao": "WMKK", "terminal": "1", "gate": null, "baggage": null, "scheduled": "2025-07-06T07:55:00+00:00", "delay": null, "estimated": null, "actual": null, "estimated_runway": null, "actual_runway": null}, "airline": {"name": "Firefly", "iata": "FY", "icao": "FFM"}, "flight": {"number": "7170", "iata": "FY7170", "icao": "FFM7170", "codeshared": {"airline_name": "malaysia airlines", "airline_iata": "mh", "airline_icao": "mas", "flight_number": "132", "flight_iata": "mh132", "flight_icao": "mas132"}}, "aircraft": null, "live": null}, {"flight_date": "2025-07-06", "flight_status": "scheduled", "departure": {"airport": "Auckland International", "timezone": "Pacific/Auckland", "iata": "AKL", "icao": "NZAA", "terminal": "I", "gate": null, "delay": null, "scheduled": "2025-07-06T00:25:00+00:00", "estimated": "2025-07-06T00:25:00+00:00", "actual": null, "estimated_runway": null, "actual_runway": null}, "arrival": {"airport": "Kuala Lumpur International Airport (klia)", "timezone": "Asia/Kuala_Lumpur", "iata": "KUL", "icao": "WMKK", "terminal": "1", "gate": null, "baggage": null, "scheduled": "2025-07-06T07:55:00+00:00", "delay": null, "estimated": null, "actual": null, "estimated_runway": null, "actual_runway": null}, "airline": {"name": "Ethiopian Airlines", "iata": "ET", "icao": "ETH"}, "flight": {"number": "4278", "iata": "ET4278", "icao": "ETH4278", "codeshared": {"airline_name": "malaysia airlines", "airline_iata": "mh", "airline_icao": "mas", "flight_number": "132", "flight_iata": "mh132", "flight_icao": "mas132"}}, "aircraft": null, "live": null}, {"flight_date": "2025-07-06", "flight_status": "scheduled", "departure": {"airport": "Auckland International", "timezone": "Pacific/Auckland", "iata": "AKL", "icao": "NZAA", "terminal": "I", "gate": null, "delay": null, "scheduled": "2025-07-06T00:25:00+00:00", "estimated": "2025-07-06T00:25:00+00:00", "actual": null, "estimated_runway": null, "actual_runway": null}, "arrival": {"airport": "Kuala Lumpur International Airport (klia)", "timezone": "Asia/Kuala_Lumpur", "iata": "KUL", "icao": "WMKK", "terminal": "1", "gate": null, "baggage": null, "scheduled": "2025-07-06T07:55:00+00:00", "delay": null, "estimated": null, "actual": null, "estimated_runway": null, "actual_runway": null}, "airline": {"name": "Myanmar Airways International", "iata": "8M", "icao": "MMA"}, "flight": {"number": "9588", "iata": "8M9588", "icao": "MMA9588", "codeshared": {"airline_name": "malaysia airlines", "airline_iata": "mh", "airline_icao": "mas", "flight_number": "132", "flight_iata": "mh132", "flight_icao": "mas132"}}, "aircraft": null, "live": null}, {"flight_date": "2025-07-05", "flight_status": "scheduled", "departure": {"airport": "Pokhara", "timezone": "Asia/Kathmandu", "iata": "PKR", "icao": "VNPK", "terminal": null, "gate": null, "delay": null, "scheduled": "2025-07-05T16:25:00+00:00", "estimated": "2025-07-05T16:25:00+00:00", "actual": null, "estimated_runway": null, "actual_runway": null}, "arrival": {"airport": "Tribhuvan International", "timezone": "Asia/Kathmandu", "iata": "KTM", "icao": "VNKT", "terminal": "D", "gate": null, "baggage": null, "scheduled": "2025-07-05T16:50:00+00:00", "delay": null, "estimated": null, "actual": null, "estimated_runway": null, "actual_runway": null}, "airline": {"name": "Sharp Airlines", "iata": "SH", "icao": "SHA"}, "flight": {"number": "662", "iata": "SH662", "icao": "SHA662", "codeshared": null}, "aircraft": null, "live": null}, {"flight_date": "2025-07-05", "flight_status": "scheduled", "departure": {"airport": "Bhairawa", "timezone": "Asia/Kathmandu", "iata": "BWA", "icao": "VNBW", "terminal": null, "gate": null, "delay": null, "scheduled": "2025-07-05T16:20:00+00:00", "estimated": "2025-07-05T16:20:00+00:00", "actual": null, "estimated_runway": null, "actual_runway": null}, "arrival": {"airport": "Tribhuvan International", "timezone": "Asia/Kathmandu", "iata": "KTM", "icao": "VNKT", "terminal": "D", "gate": null, "baggage": null, "scheduled": "2025-07-05T16:50:00+00:00", "delay": null, "estimated": null, "actual": null, "estimated_runway": null, "actual_runway": null}, "airline": {"name": "Yeti Airlines", "iata": "YT", "icao": "NYT"}, "flight": {"number": "878", "iata": "YT878", "icao": "NYT878", "codeshared": null}, "aircraft": null, "live": null}, {"flight_date": "2025-07-05", "flight_status": "scheduled", "departure": {"airport": "Dublin International", "timezone": "Europe/Dublin", "iata": "DUB", "icao": "EIDW", "terminal": null, "gate": null, "delay": 630, "scheduled": "2025-07-05T08:00:00+00:00", "estimated": "2025-07-05T08:00:00+00:00", "actual": null, "estimated_runway": null, "actual_runway": null}, "arrival": {"airport": "Dyce", "timezone": "Europe/London", "iata": "ABZ", "icao": "EGPD", "terminal": null, "gate": null, "baggage": null, "scheduled": "2025-07-05T09:20:00+00:00", "delay": null, "estimated": null, "actual": null, "estimated_runway": null, "actual_runway": null}, "airline": {"name": "Aer Lingus", "iata": "EI", "icao": "EIN"}, "flight": {"number": "3242", "iata": "EI3242", "icao": "EIN3242", "codeshared": null}, "aircraft": null, "live": null}, {"flight_date": "2025-07-05", "flight_status": "scheduled", "departure": {"airport": "Dublin International", "timezone": "Europe/Dublin", "iata": "DUB", "icao": "EIDW", "terminal": null, "gate": null, "delay": 630, "scheduled": "2025-07-05T08:00:00+00:00", "estimated": "2025-07-05T08:00:00+00:00", "actual": null, "estimated_runway": null, "actual_runway": null}, "arrival": {"airport": "Dyce", "timezone": "Europe/London", "iata": "ABZ", "icao": "EGPD", "terminal": null, "gate": null, "baggage": null, "scheduled": "2025-07-05T09:20:00+00:00", "delay": null, "estimated": null, "actual": null, "estimated_runway": null, "actual_runway": null}, "airline": {"name": "Qatar Airways", "iata": "QR", "icao": "QTR"}, "flight": {"number": "8243", "iata": "QR8243", "icao": "QTR8243", "codeshared": {"airline_name": "aer lingus", "airline_iata": "ei", "airline_icao": "ein", "flight_number": "3242", "flight_iata": "ei3242", "flight_icao": "ein3242"}}, "aircraft": null, "live": null}, {"flight_date": "2025-07-05", "flight_status": "scheduled", "departure": {"airport": "Dublin International", "timezone": "Europe/Dublin", "iata": "DUB", "icao": "EIDW", "terminal": null, "gate": null, "delay": 630, "scheduled": "2025-07-05T08:00:00+00:00", "estimated": "2025-07-05T08:00:00+00:00", "actual": null, "estimated_runway": null, "actual_runway": null}, "arrival": {"airport": "Dyce", "timezone": "Europe/London", "iata": "ABZ", "icao": "EGPD", "terminal": null, "gate": null, "baggage": null, "scheduled": "2025-07-05T09:20:00+00:00", "delay": null, "estimated": null, "actual": null, "estimated_runway": null, "actual_runway": null}, "airline": {"name": "British Airways", "iata": "BA", "icao": "BAW"}, "flight": {"number": "8982", "iata": "BA8982", "icao": "BAW8982", "codeshared": {"airline_name": "aer lingus", "airline_iata": "ei", "airline_icao": "ein", "flight_number": "3242", "flight_iata": "ei3242", "flight_icao": "ein3242"}}, "aircraft": null, "live": null}, {"flight_date": "2025-07-05", "flight_status": "active", "departure": {"airport": "Albury", "timezone": "Australia/Sydney", "iata": "ABX", "icao": "YMAY", "terminal": null, "gate": null, "delay": 12, "scheduled": "2025-07-05T10:10:00+00:00", "estimated": "2025-07-05T10:10:00+00:00", "actual": "2025-07-05T10:21:00+00:00", "estimated_runway": "2025-07-05T10:21:00+00:00", "actual_runway": "2025-07-05T10:21:00+00:00"}, "arrival": {"airport": "Sydney Kingsford Smith Airport", "timezone": "Australia/Sydney", "iata": "SYD", "icao": "YSSY", "terminal": "3", "gate": "16", "baggage": "QFR", "scheduled": "2025-07-05T11:30:00+00:00", "delay": null, "estimated": null, "actual": null, "estimated_runway": null, "actual_runway": null}, "airline": {"name": "QantasLink", "iata": null, "icao": "QLK"}, "flight": {"number": "2204", "iata": null, "icao": "QLK2204", "codeshared": null}, "aircraft": null, "live": null}, {"flight_date": "2025-07-05", "flight_status": "active", "departure": {"airport": "Beijing Capital International", "timezone": "Asia/Shanghai", "iata": "PEK", "icao": "ZBAA", "terminal": "3", "gate": "J,K", "delay": 110, "scheduled": "2025-07-05T14:30:00+00:00", "estimated": "2025-07-05T14:30:00+00:00", "actual": null, "estimated_runway": null, "actual_runway": null}, "arrival": {"airport": "Urumqi", "timezone": "Asia/Shanghai", "iata": "URC", "icao": "ZWWW", "terminal": null, "gate": null, "baggage": null, "scheduled": "2025-07-05T18:40:00+00:00", "delay": null, "estimated": null, "actual": null, "estimated_runway": null, "actual_runway": null}, "airline": {"name": "Shenzhen Airlines", "iata": "ZH", "icao": "CSZ"}, "flight": {"number": "1293", "iata": "ZH1293", "icao": "CSZ1293", "codeshared": {"airline_name": "air china ltd", "airline_iata": "ca", "airline_icao": "cca", "flight_number": "1293", "flight_iata": "ca1293", "flight_icao": "cca1293"}}, "aircraft": null, "live": null}, {"flight_date": "2025-07-05", "flight_status": "active", "departure": {"airport": "Beijing Capital International", "timezone": "Asia/Shanghai", "iata": "PEK", "icao": "ZBAA", "terminal": "3", "gate": "J,K", "delay": 110, "scheduled": "2025-07-05T14:30:00+00:00", "estimated": "2025-07-05T14:30:00+00:00", "actual": null, "estimated_runway": null, "actual_runway": null}, "arrival": {"airport": "Urumqi", "timezone": "Asia/Shanghai", "iata": "URC", "icao": "ZWWW", "terminal": null, "gate": null, "baggage": null, "scheduled": "2025-07-05T18:40:00+00:00", "delay": null, "estimated": null, "actual": null, "estimated_runway": null, "actual_runway": null}, "airline": {"name": "Shandong Airlines", "iata": "SC", "icao": "CDG"}, "flight": {"number": "5721", "iata": "SC5721", "icao": "CDG5721", "codeshared": {"airline_name": "air china ltd", "airline_iata": "ca", "airline_icao": "cca", "flight_number": "1293", "flight_iata": "ca1293", "flight_icao": "cca1293"}}, "aircraft": null, "live": null}, {"flight_date": "2025-07-05", "flight_status": "scheduled", "departure": {"airport": "Portland International", "timezone": "America/Los_Angeles", "iata": "PDX", "icao": "KPDX", "terminal": null, "gate": "D15", "delay": null, "scheduled": "2025-07-05T06:55:00+00:00", "estimated": "2025-07-05T06:55:00+00:00", "actual": null, "estimated_runway": null, "actual_runway": null}, "arrival": {"airport": "John F Kennedy International", "timezone": "America/New_York", "iata": "JFK", "icao": "KJFK", "terminal": "4", "gate": "B55", "baggage": null, "scheduled": "2025-07-05T15:25:00+00:00", "delay": null, "estimated": null, "actual": null, "estimated_runway": null, "actual_runway": null}, "airline": {"name": "Delta Air Lines", "iata": "DL", "icao": "DAL"}, "flight": {"number": "451", "iata": "DL451", "icao": "DAL451", "codeshared": null}, "aircraft": null, "live": null}, {"flight_date": "2025-07-05", "flight_status": "scheduled", "departure": {"airport": "Portland International", "timezone": "America/Los_Angeles", "iata": "PDX", "icao": "KPDX", "terminal": null, "gate": "D15", "delay": null, "scheduled": "2025-07-05T06:55:00+00:00", "estimated": "2025-07-05T06:55:00+00:00", "actual": null, "estimated_runway": null, "actual_runway": null}, "arrival": {"airport": "John F Kennedy International", "timezone": "America/New_York", "iata": "JFK", "icao": "KJFK", "terminal": "4", "gate": "B55", "baggage": null, "scheduled": "2025-07-05T15:25:00+00:00", "delay": null, "estimated": null, "actual": null, "estimated_runway": null, "actual_runway": null}, "airline": {"name": "Virgin Atlantic", "iata": "VS", "icao": "VIR"}, "flight": {"number": "4850", "iata": "VS4850", "icao": "VIR4850", "codeshared": {"airline_name": "delta air lines", "airline_iata": "dl", "airline_icao": "dal", "flight_number": "451", "flight_iata": "dl451", "flight_icao": "dal451"}}, "aircraft": null, "live": null}, {"flight_date": "2025-07-05", "flight_status": "scheduled", "departure": {"airport": "Portland International", "timezone": "America/Los_Angeles", "iata": "PDX", "icao": "KPDX", "terminal": null, "gate": "D15", "delay": null, "scheduled": "2025-07-05T06:55:00+00:00", "estimated": "2025-07-05T06:55:00+00:00", "actual": null, "estimated_runway": null, "actual_runway": null}, "arrival": {"airport": "John F Kennedy International", "timezone": "America/New_York", "iata": "JFK", "icao": "KJFK", "terminal": "4", "gate": "B55", "baggage": null, "scheduled": "2025-07-05T15:25:00+00:00", "delay": null, "estimated": null, "actual": null, "estimated_runway": null, "actual_runway": null}, "airline": {"name": "Air Europa", "iata": "UX", "icao": "AEA"}, "flight": {"number": "3428", "iata": "UX3428", "icao": "AEA3428", "codeshared": {"airline_name": "delta air lines", "airline_iata": "dl", "airline_icao": "dal", "flight_number": "451", "flight_iata": "dl451", "flight_icao": "dal451"}}, "aircraft": null, "live": null}, {"flight_date": "2025-07-05", "flight_status": "scheduled", "departure": {"airport": "Portland International", "timezone": "America/Los_Angeles", "iata": "PDX", "icao": "KPDX", "terminal": null, "gate": "D15", "delay": null, "scheduled": "2025-07-05T06:55:00+00:00", "estimated": "2025-07-05T06:55:00+00:00", "actual": null, "estimated_runway": null, "actual_runway": null}, "arrival": {"airport": "John F Kennedy International", "timezone": "America/New_York", "iata": "JFK", "icao": "KJFK", "terminal": "4", "gate": "B55", "baggage": null, "scheduled": "2025-07-05T15:25:00+00:00", "delay": null, "estimated": null, "actual": null, "estimated_runway": null, "actual_runway": null}, "airline": {"name": "SAS", "iata": "SK", "icao": "SAS"}, "flight": {"number": "3415", "iata": "SK3415", "icao": "SAS3415", "codeshared": {"airline_name": "delta air lines", "airline_iata": "dl", "airline_icao": "dal", "flight_number": "451", "flight_iata": "dl451", "flight_icao": "dal451"}}, "aircraft": null, "live": null}, {"flight_date": "2025-07-05", "flight_status": "scheduled", "departure": {"airport": "Portland International", "timezone": "America/Los_Angeles", "iata": "PDX", "icao": "KPDX", "terminal": null, "gate": "D15", "delay": null, "scheduled": "2025-07-05T06:55:00+00:00", "estimated": "2025-07-05T06:55:00+00:00", "actual": null, "estimated_runway": null, "actual_runway": null}, "arrival": {"airport": "John F Kennedy International", "timezone": "America/New_York", "iata": "JFK", "icao": "KJFK", "terminal": "4", "gate": "B55", "baggage": null, "scheduled": "2025-07-05T15:25:00+00:00", "delay": null, "estimated": null, "actual": null, "estimated_runway": null, "actual_runway": null}, "airline": {"name": "LATAM Airlines", "iata": "LA", "icao": "LAN"}, "flight": {"number": "6631", "iata": "LA6631", "icao": "LAN6631", "codeshared": {"airline_name": "delta air lines", "airline_iata": "dl", "airline_icao": "dal", "flight_number": "451", "flight_iata": "dl451", "flight_icao": "dal451"}}, "aircraft": null, "live": null}, {"flight_date": "2025-07-05", "flight_status": "scheduled", "departure": {"airport": "Portland International", "timezone": "America/Los_Angeles", "iata": "PDX", "icao": "KPDX", "terminal": null, "gate": "D15", "delay": null, "scheduled": "2025-07-05T06:55:00+00:00", "estimated": "2025-07-05T06:55:00+00:00", "actual": null, "estimated_runway": null, "actual_runway": null}, "arrival": {"airport": "John F Kennedy International", "timezone": "America/New_York", "iata": "JFK", "icao": "KJFK", "terminal": "4", "gate": "B55", "baggage": null, "scheduled": "2025-07-05T15:25:00+00:00", "delay": null, "estimated": null, "actual": null, "estimated_runway": null, "actual_runway": null}, "airline": {"name": "Alitalia", "iata": "AZ", "icao": "AZA"}, "flight": {"number": "3273", "iata": "AZ3273", "icao": "AZA3273", "codeshared": {"airline_name": "delta air lines", "airline_iata": "dl", "airline_icao": "dal", "flight_number": "451", "flight_iata": "dl451", "flight_icao": "dal451"}}, "aircraft": null, "live": null}, {"flight_date": "2025-07-05", "flight_status": "scheduled", "departure": {"airport": "Portland International", "timezone": "America/Los_Angeles", "iata": "PDX", "icao": "KPDX", "terminal": null, "gate": "D15", "delay": null, "scheduled": "2025-07-05T06:55:00+00:00", "estimated": "2025-07-05T06:55:00+00:00", "actual": null, "estimated_runway": null, "actual_runway": null}, "arrival": {"airport": "John F Kennedy International", "timezone": "America/New_York", "iata": "JFK", "icao": "KJFK", "terminal": "4", "gate": "B55", "baggage": null, "scheduled": "2025-07-05T15:25:00+00:00", "delay": null, "estimated": null, "actual": null, "estimated_runway": null, "actual_runway": null}, "airline": {"name": "Air France", "iata": "AF", "icao": "AFR"}, "flight": {"number": "8535", "iata": "AF8535", "icao": "AFR8535", "codeshared": {"airline_name": "delta air lines", "airline_iata": "dl", "airline_icao": "dal", "flight_number": "451", "flight_iata": "dl451", "flight_icao": "dal451"}}, "aircraft": null, "live": null}, {"flight_date": "2025-07-05", "flight_status": "scheduled", "departure": {"airport": "Portland International", "timezone": "America/Los_Angeles", "iata": "PDX", "icao": "KPDX", "terminal": null, "gate": "E10", "delay": 11, "scheduled": "2025-07-05T06:40:00+00:00", "estimated": "2025-07-05T06:40:00+00:00", "actual": null, "estimated_runway": null, "actual_runway": null}, "arrival": {"airport": "Mineta San Jose International Airport", "timezone": "America/Los_Angeles", "iata": "SJC", "icao": "KSJC", "terminal": "B", "gate": "24", "baggage": null, "scheduled": "2025-07-05T08:25:00+00:00", "delay": null, "estimated": null, "actual": null, "estimated_runway": null, "actual_runway": null}, "airline": {"name": "Southwest Airlines", "iata": "WN", "icao": "SWA"}, "flight": {"number": "1722", "iata": "WN1722", "icao": "SWA1722", "codeshared": null}, "aircraft": null, "live": null}, {"flight_date": "2025-07-05", "flight_status": "scheduled", "departure": {"airport": "Portland International", "timezone": "America/Los_Angeles", "iata": "PDX", "icao": "KPDX", "terminal": null, "gate": null, "delay": 12, "scheduled": "2025-07-05T06:35:00+00:00", "estimated": "2025-07-05T06:35:00+00:00", "actual": null, "estimated_runway": null, "actual_runway": null}, "arrival": {"airport": "Louisville International (Standiford Field)", "timezone": "America/Kentucky/Louisville", "iata": "SDF", "icao": "KSDF", "terminal": null, "gate": null, "baggage": null, "scheduled": "2025-07-05T13:21:00+00:00", "delay": null, "estimated": null, "actual": null, "estimated_runway": null, "actual_runway": null}, "airline": {"name": "UPS Airlines", "iata": "5X", "icao": "UPS"}, "flight": {"number": "5973", "iata": "5X5973", "icao": "UPS5973", "codeshared": null}, "aircraft": null, "live": null}, {"flight_date": "2025-07-05", "flight_status": "scheduled", "departure": {"airport": "Portland International", "timezone": "America/Los_Angeles", "iata": "PDX", "icao": "KPDX", "terminal": null, "gate": "C16", "delay": null, "scheduled": "2025-07-05T06:35:00+00:00", "estimated": "2025-07-05T06:35:00+00:00", "actual": null, "estimated_runway": null, "actual_runway": null}, "arrival": {"airport": "Denver International", "timezone": "America/Denver", "iata": "DEN", "icao": "KDEN", "terminal": null, "gate": null, "baggage": "7", "scheduled": "2025-07-05T10:14:00+00:00", "delay": null, "estimated": null, "actual": null, "estimated_runway": null, "actual_runway": null}, "airline": {"name": "Frontier Airlines", "iata": "F9", "icao": "FFT"}, "flight": {"number": "1790", "iata": "F91790", "icao": "FFT1790", "codeshared": null}, "aircraft": null, "live": null}, {"flight_date": "2025-07-05", "flight_status": "scheduled", "departure": {"airport": "Portland International", "timezone": "America/Los_Angeles", "iata": "PDX", "icao": "KPDX", "terminal": null, "gate": "C16", "delay": null, "scheduled": "2025-07-05T06:35:00+00:00", "estimated": "2025-07-05T06:35:00+00:00", "actual": null, "estimated_runway": null, "actual_runway": null}, "arrival": {"airport": "Denver International", "timezone": "America/Denver", "iata": "DEN", "icao": "KDEN", "terminal": null, "gate": null, "baggage": "7", "scheduled": "2025-07-05T10:14:00+00:00", "delay": null, "estimated": null, "actual": null, "estimated_runway": null, "actual_runway": null}, "airline": {"name": "Volaris", "iata": "Y4", "icao": "VOI"}, "flight": {"number": "2278", "iata": "Y42278", "icao": "VOI2278", "codeshared": {"airline_name": "frontier airlines", "airline_iata": "f9", "airline_icao": "fft", "flight_number": "1790", "flight_iata": "f91790", "flight_icao": "fft1790"}}, "aircraft": null, "live": null}, {"flight_date": "2025-07-05", "flight_status": "scheduled", "departure": {"airport": "Portland International", "timezone": "America/Los_Angeles", "iata": "PDX", "icao": "KPDX", "terminal": null, "gate": "D5", "delay": null, "scheduled": "2025-07-05T06:25:00+00:00", "estimated": "2025-07-05T06:25:00+00:00", "actual": null, "estimated_runway": null, "actual_runway": null}, "arrival": {"airport": "Minneapolis - St. Paul International", "timezone": "America/Chicago", "iata": "MSP", "icao": "KMSP", "terminal": "1", "gate": "G18", "baggage": "6", "scheduled": "2025-07-05T11:43:00+00:00", "delay": null, "estimated": null, "actual": null, "estimated_runway": null, "actual_runway": null}, "airline": {"name": "Delta Air Lines", "iata": "DL", "icao": "DAL"}, "flight": {"number": "2369", "iata": "DL2369", "icao": "DAL2369", "codeshared": null}, "aircraft": null, "live": null}, {"flight_date": "2025-07-05", "flight_status": "scheduled", "departure": {"airport": "Portland International", "timezone": "America/Los_Angeles", "iata": "PDX", "icao": "KPDX", "terminal": null, "gate": "D5", "delay": null, "scheduled": "2025-07-05T06:25:00+00:00", "estimated": "2025-07-05T06:25:00+00:00", "actual": null, "estimated_runway": null, "actual_runway": null}, "arrival": {"airport": "Minneapolis - St. Paul International", "timezone": "America/Chicago", "iata": "MSP", "icao": "KMSP", "terminal": "1", "gate": "G18", "baggage": "6", "scheduled": "2025-07-05T11:43:00+00:00", "delay": null, "estimated": null, "actual": null, "estimated_runway": null, "actual_runway": null}, "airline": {"name": "WestJet", "iata": "WS", "icao": "WJA"}, "flight": {"number": "8313", "iata": "WS8313", "icao": "WJA8313", "codeshared": {"airline_name": "delta air lines", "airline_iata": "dl", "airline_icao": "dal", "flight_number": "2369", "flight_iata": "dl2369", "flight_icao": "dal2369"}}, "aircraft": null, "live": null}, {"flight_date": "2025-07-05", "flight_status": "scheduled", "departure": {"airport": "Portland International", "timezone": "America/Los_Angeles", "iata": "PDX", "icao": "KPDX", "terminal": null, "gate": "D5", "delay": null, "scheduled": "2025-07-05T06:25:00+00:00", "estimated": "2025-07-05T06:25:00+00:00", "actual": null, "estimated_runway": null, "actual_runway": null}, "arrival": {"airport": "Minneapolis - St. Paul International", "timezone": "America/Chicago", "iata": "MSP", "icao": "KMSP", "terminal": "1", "gate": "G18", "baggage": "6", "scheduled": "2025-07-05T11:43:00+00:00", "delay": null, "estimated": null, "actual": null, "estimated_runway": null, "actual_runway": null}, "airline": {"name": "Korean Air", "iata": "KE", "icao": "KAL"}, "flight": {"number": "6748", "iata": "KE6748", "icao": "KAL6748", "codeshared": {"airline_name": "delta air lines", "airline_iata": "dl", "airline_icao": "dal", "flight_number": "2369", "flight_iata": "dl2369", "flight_icao": "dal2369"}}, "aircraft": null, "live": null}, {"flight_date": "2025-07-05", "flight_status": "scheduled", "departure": {"airport": "Portland International", "timezone": "America/Los_Angeles", "iata": "PDX", "icao": "KPDX", "terminal": null, "gate": "D5", "delay": null, "scheduled": "2025-07-05T06:25:00+00:00", "estimated": "2025-07-05T06:25:00+00:00", "actual": null, "estimated_runway": null, "actual_runway": null}, "arrival": {"airport": "Minneapolis - St. Paul International", "timezone": "America/Chicago", "iata": "MSP", "icao": "KMSP", "terminal": "1", "gate": "G18", "baggage": "6", "scheduled": "2025-07-05T11:43:00+00:00", "delay": null, "estimated": null, "actual": null, "estimated_runway": null, "actual_runway": null}, "airline": {"name": "Air France", "iata": "AF", "icao": "AFR"}, "flight": {"number": "2124", "iata": "AF2124", "icao": "AFR2124", "codeshared": {"airline_name": "delta air lines", "airline_iata": "dl", "airline_icao": "dal", "flight_number": "2369", "flight_iata": "dl2369", "flight_icao": "dal2369"}}, "aircraft": null, "live": null}, {"flight_date": "2025-07-05", "flight_status": "scheduled", "departure": {"airport": "Portland International", "timezone": "America/Los_Angeles", "iata": "PDX", "icao": "KPDX", "terminal": null, "gate": null, "delay": 8, "scheduled": "2025-07-05T06:20:00+00:00", "estimated": "2025-07-05T06:20:00+00:00", "actual": null, "estimated_runway": null, "actual_runway": null}, "arrival": {"airport": "Greater Rockford Airport", "timezone": "America/Chicago", "iata": "RFD", "icao": "KRFD", "terminal": null, "gate": null, "baggage": null, "scheduled": "2025-07-05T11:42:00+00:00", "delay": null, "estimated": null, "actual": null, "estimated_runway": null, "actual_runway": null}, "airline": {"name": "UPS Airlines", "iata": "5X", "icao": "UPS"}, "flight": {"number": "5975", "iata": "5X5975", "icao": "UPS5975", "codeshared": null}, "aircraft": null, "live": null}, {"flight_date": "2025-07-05", "flight_status": "scheduled", "departure": {"airport": "Portland International", "timezone": "America/Los_Angeles", "iata": "PDX", "icao": "KPDX", "terminal": null, "gate": "E11", "delay": 11, "scheduled": "2025-07-05T06:20:00+00:00", "estimated": "2025-07-05T06:20:00+00:00", "actual": null, "estimated_runway": null, "actual_runway": null}, "arrival": {"airport": "Midway", "timezone": "America/Chicago", "iata": "MDW", "icao": "KMDW", "terminal": null, "gate": "B2", "baggage": null, "scheduled": "2025-07-05T12:15:00+00:00", "delay": null, "estimated": null, "actual": null, "estimated_runway": null, "actual_runway": null}, "airline": {"name": "Southwest Airlines", "iata": "WN", "icao": "SWA"}, "flight": {"number": "2735", "iata": "WN2735", "icao": "SWA2735", "codeshared": null}, "aircraft": null, "live": null}, {"flight_date": "2025-07-05", "flight_status": "scheduled", "departure": {"airport": "Portland International", "timezone": "America/Los_Angeles", "iata": "PDX", "icao": "KPDX", "terminal": null, "gate": "E13", "delay": 4, "scheduled": "2025-07-05T06:15:00+00:00", "estimated": "2025-07-05T06:15:00+00:00", "actual": null, "estimated_runway": null, "actual_runway": null}, "arrival": {"airport": "Vancouver International", "timezone": "America/Vancouver", "iata": "YVR", "icao": "CYVR", "terminal": "M", "gate": "E87", "baggage": "33", "scheduled": "2025-07-05T07:32:00+00:00", "delay": null, "estimated": null, "actual": null, "estimated_runway": null, "actual_runway": null}, "airline": {"name": "Air Canada", "iata": "AC", "icao": "ACA"}, "flight": {"number": "8649", "iata": "AC8649", "icao": "ACA8649", "codeshared": null}, "aircraft": null, "live": null}, {"flight_date": "2025-07-05", "flight_status": "scheduled", "departure": {"airport": "Portland International", "timezone": "America/Los_Angeles", "iata": "PDX", "icao": "KPDX", "terminal": null, "gate": "E13", "delay": 4, "scheduled": "2025-07-05T06:15:00+00:00", "estimated": "2025-07-05T06:15:00+00:00", "actual": null, "estimated_runway": null, "actual_runway": null}, "arrival": {"airport": "Vancouver International", "timezone": "America/Vancouver", "iata": "YVR", "icao": "CYVR", "terminal": "M", "gate": "E87", "baggage": "33", "scheduled": "2025-07-05T07:32:00+00:00", "delay": null, "estimated": null, "actual": null, "estimated_runway": null, "actual_runway": null}, "airline": {"name": "United Airlines", "iata": "UA", "icao": "UAL"}, "flight": {"number": "8216", "iata": "UA8216", "icao": "UAL8216", "codeshared": {"airline_name": "air canada", "airline_iata": "ac", "airline_icao": "aca", "flight_number": "8649", "flight_iata": "ac8649", "flight_icao": "aca8649"}}, "aircraft": null, "live": null}, {"flight_date": "2025-07-05", "flight_status": "scheduled", "departure": {"airport": "Portland International", "timezone": "America/Los_Angeles", "iata": "PDX", "icao": "KPDX", "terminal": null, "gate": "E13", "delay": 4, "scheduled": "2025-07-05T06:15:00+00:00", "estimated": "2025-07-05T06:15:00+00:00", "actual": null, "estimated_runway": null, "actual_runway": null}, "arrival": {"airport": "Vancouver International", "timezone": "America/Vancouver", "iata": "YVR", "icao": "CYVR", "terminal": "M", "gate": "E87", "baggage": "33", "scheduled": "2025-07-05T07:32:00+00:00", "delay": null, "estimated": null, "actual": null, "estimated_runway": null, "actual_runway": null}, "airline": {"name": "Air New Zealand", "iata": "NZ", "icao": "ANZ"}, "flight": {"number": "4699", "iata": "NZ4699", "icao": "ANZ4699", "codeshared": {"airline_name": "air canada", "airline_iata": "ac", "airline_icao": "aca", "flight_number": "8649", "flight_iata": "ac8649", "flight_icao": "aca8649"}}, "aircraft": null, "live": null}, {"flight_date": "2025-07-05", "flight_status": "scheduled", "departure": {"airport": "Portland International", "timezone": "America/Los_Angeles", "iata": "PDX", "icao": "KPDX", "terminal": null, "gate": "D11", "delay": null, "scheduled": "2025-07-05T06:15:00+00:00", "estimated": "2025-07-05T06:15:00+00:00", "actual": null, "estimated_runway": null, "actual_runway": null}, "arrival": {"airport": "Los Angeles International", "timezone": "America/Los_Angeles", "iata": "LAX", "icao": "KLAX", "terminal": "2", "gate": "23B", "baggage": null, "scheduled": "2025-07-05T08:44:00+00:00", "delay": null, "estimated": null, "actual": null, "estimated_runway": null, "actual_runway": null}, "airline": {"name": "Delta Air Lines", "iata": "DL", "icao": "DAL"}, "flight": {"number": "2947", "iata": "DL2947", "icao": "DAL2947", "codeshared": null}, "aircraft": null, "live": null}, {"flight_date": "2025-07-05", "flight_status": "scheduled", "departure": {"airport": "Portland International", "timezone": "America/Los_Angeles", "iata": "PDX", "icao": "KPDX", "terminal": null, "gate": "D11", "delay": null, "scheduled": "2025-07-05T06:15:00+00:00", "estimated": "2025-07-05T06:15:00+00:00", "actual": null, "estimated_runway": null, "actual_runway": null}, "arrival": {"airport": "Los Angeles International", "timezone": "America/Los_Angeles", "iata": "LAX", "icao": "KLAX", "terminal": "2", "gate": "23B", "baggage": null, "scheduled": "2025-07-05T08:44:00+00:00", "delay": null, "estimated": null, "actual": null, "estimated_runway": null, "actual_runway": null}, "airline": {"name": "Virgin Atlantic", "iata": "VS", "icao": "VIR"}, "flight": {"number": "4156", "iata": "VS4156", "icao": "VIR4156", "codeshared": {"airline_name": "delta air lines", "airline_iata": "dl", "airline_icao": "dal", "flight_number": "2947", "flight_iata": "dl2947", "flight_icao": "dal2947"}}, "aircraft": null, "live": null}, {"flight_date": "2025-07-05", "flight_status": "scheduled", "departure": {"airport": "Portland International", "timezone": "America/Los_Angeles", "iata": "PDX", "icao": "KPDX", "terminal": null, "gate": "D11", "delay": null, "scheduled": "2025-07-05T06:15:00+00:00", "estimated": "2025-07-05T06:15:00+00:00", "actual": null, "estimated_runway": null, "actual_runway": null}, "arrival": {"airport": "Los Angeles International", "timezone": "America/Los_Angeles", "iata": "LAX", "icao": "KLAX", "terminal": "2", "gate": "23B", "baggage": null, "scheduled": "2025-07-05T08:44:00+00:00", "delay": null, "estimated": null, "actual": null, "estimated_runway": null, "actual_runway": null}, "airline": {"name": "China Eastern Airlines", "iata": "MU", "icao": "CES"}, "flight": {"number": "8798", "iata": "MU8798", "icao": "CES8798", "codeshared": {"airline_name": "delta air lines", "airline_iata": "dl", "airline_icao": "dal", "flight_number": "2947", "flight_iata": "dl2947", "flight_icao": "dal2947"}}, "aircraft": null, "live": null}, {"flight_date": "2025-07-05", "flight_status": "scheduled", "departure": {"airport": "Korla", "timezone": "Asia/Shanghai", "iata": "KRL", "icao": "ZWKL", "terminal": null, "gate": null, "delay": null, "scheduled": "2025-07-05T21:50:00+00:00", "estimated": "2025-07-05T21:50:00+00:00", "actual": null, "estimated_runway": null, "actual_runway": null}, "arrival": {"airport": "Urumqi", "timezone": "Asia/Shanghai", "iata": "URC", "icao": "ZWWW", "terminal": "2", "gate": null, "baggage": null, "scheduled": "2025-07-05T22:45:00+00:00", "delay": null, "estimated": null, "actual": null, "estimated_runway": null, "actual_runway": null}, "airline": {"name": "Tianjin Airlines", "iata": "GS", "icao": "GCR"}, "flight": {"number": "7472", "iata": "GS7472", "icao": "GCR7472", "codeshared": null}, "aircraft": null, "live": null}, {"flight_date": "2025-07-05", "flight_status": "scheduled", "departure": {"airport": "Korla", "timezone": "Asia/Shanghai", "iata": "KRL", "icao": "ZWKL", "terminal": null, "gate": null, "delay": null, "scheduled": "2025-07-05T21:05:00+00:00", "estimated": "2025-07-05T21:05:00+00:00", "actual": null, "estimated_runway": null, "actual_runway": null}, "arrival": {"airport": "Zhengzhou", "timezone": "Asia/Shanghai", "iata": "CGO", "icao": "ZHCC", "terminal": "T2", "gate": null, "baggage": null, "scheduled": "2025-07-06T01:05:00+00:00", "delay": null, "estimated": null, "actual": null, "estimated_runway": null, "actual_runway": null}, "airline": {"name": "West Air (China)", "iata": "PN", "icao": "CHB"}, "flight": {"number": "6390", "iata": "PN6390", "icao": "CHB6390", "codeshared": null}, "aircraft": null, "live": null}, {"flight_date": "2025-07-05", "flight_status": "scheduled", "departure": {"airport": "Korla", "timezone": "Asia/Shanghai", "iata": "KRL", "icao": "ZWKL", "terminal": null, "gate": null, "delay": null, "scheduled": "2025-07-05T20:15:00+00:00", "estimated": "2025-07-05T20:15:00+00:00", "actual": null, "estimated_runway": null, "actual_runway": null}, "arrival": {"airport": "Beijing Capital International", "timezone": "Asia/Shanghai", "iata": "PEK", "icao": "ZBAA", "terminal": "2", "gate": null, "baggage": "17", "scheduled": "2025-07-06T00:30:00+00:00", "delay": null, "estimated": null, "actual": null, "estimated_runway": null, "actual_runway": null}, "airline": {"name": "Air China LTD", "iata": "CA", "icao": "CCA"}, "flight": {"number": "1260", "iata": "CA1260", "icao": "CCA1260", "codeshared": null}, "aircraft": null, "live": null}, {"flight_date": "2025-07-05", "flight_status": "scheduled", "departure": {"airport": "Korla", "timezone": "Asia/Shanghai", "iata": "KRL", "icao": "ZWKL", "terminal": null, "gate": null, "delay": null, "scheduled": "2025-07-05T20:15:00+00:00", "estimated": "2025-07-05T20:15:00+00:00", "actual": null, "estimated_runway": null, "actual_runway": null}, "arrival": {"airport": "Beijing Capital International", "timezone": "Asia/Shanghai", "iata": "PEK", "icao": "ZBAA", "terminal": "2", "gate": null, "baggage": "17", "scheduled": "2025-07-06T00:30:00+00:00", "delay": null, "estimated": null, "actual": null, "estimated_runway": null, "actual_runway": null}, "airline": {"name": "Shenzhen Airlines", "iata": "ZH", "icao": "CSZ"}, "flight": {"number": "1260", "iata": "ZH1260", "icao": "CSZ1260", "codeshared": {"airline_name": "air china ltd", "airline_iata": "ca", "airline_icao": "cca", "flight_number": "1260", "flight_iata": "ca1260", "flight_icao": "cca1260"}}, "aircraft": null, "live": null}, {"flight_date": "2025-07-05", "flight_status": "active", "departure": {"airport": "Haneda Airport", "timezone": "Asia/Tokyo", "iata": "HND", "icao": "RJTT", "terminal": "3", "gate": "145", "delay": 13, "scheduled": "2025-07-05T11:30:00+00:00", "estimated": "2025-07-05T11:30:00+00:00", "actual": "2025-07-05T11:42:00+00:00", "estimated_runway": "2025-07-05T11:42:00+00:00", "actual_runway": "2025-07-05T11:42:00+00:00"}, "arrival": {"airport": "Chicago O'hare International", "timezone": "America/Chicago", "iata": "ORD", "icao": "KORD", "terminal": "5", "gate": null, "baggage": null, "scheduled": "2025-07-05T09:15:00+00:00", "delay": null, "estimated": null, "actual": null, "estimated_runway": null, "actual_runway": null}, "airline": {"name": "Malaysia Airlines", "iata": "MH", "icao": "MAS"}, "flight": {"number": "9110", "iata": "MH9110", "icao": "MAS9110", "codeshared": {"airline_name": "japan airlines (oneworld livery)", "airline_iata": "jl", "airline_icao": "jal", "flight_number": "10", "flight_iata": "jl10", "flight_icao": "jal10"}}, "aircraft": null, "live": null}, {"flight_date": "2025-07-05", "flight_status": "active", "departure": {"airport": "Haneda Airport", "timezone": "Asia/Tokyo", "iata": "HND", "icao": "RJTT", "terminal": "3", "gate": "145", "delay": 13, "scheduled": "2025-07-05T11:30:00+00:00", "estimated": "2025-07-05T11:30:00+00:00", "actual": "2025-07-05T11:42:00+00:00", "estimated_runway": "2025-07-05T11:42:00+00:00", "actual_runway": "2025-07-05T11:42:00+00:00"}, "arrival": {"airport": "Chicago O'hare International", "timezone": "America/Chicago", "iata": "ORD", "icao": "KORD", "terminal": "5", "gate": null, "baggage": null, "scheduled": "2025-07-05T09:15:00+00:00", "delay": null, "estimated": null, "actual": null, "estimated_runway": null, "actual_runway": null}, "airline": {"name": "American Airlines", "iata": "AA", "icao": "AAL"}, "flight": {"number": "8405", "iata": "AA8405", "icao": "AAL8405", "codeshared": {"airline_name": "japan airlines (oneworld livery)", "airline_iata": "jl", "airline_icao": "jal", "flight_number": "10", "flight_iata": "jl10", "flight_icao": "jal10"}}, "aircraft": null, "live": null}, {"flight_date": "2025-07-05", "flight_status": "scheduled", "departure": {"airport": "Minangkabau International Airport", "timezone": "Asia/Jakarta", "iata": "PDG", "icao": "WIEE", "terminal": null, "gate": null, "delay": null, "scheduled": "2025-07-05T17:35:00+00:00", "estimated": "2025-07-05T17:35:00+00:00", "actual": null, "estimated_runway": null, "actual_runway": null}, "arrival": {"airport": "Soekarno-Hatta International", "timezone": "Asia/Jakarta", "iata": "CGK", "icao": "WIII", "terminal": "3", "gate": null, "baggage": null, "scheduled": "2025-07-05T19:30:00+00:00", "delay": null, "estimated": null, "actual": null, "estimated_runway": null, "actual_runway": null}, "airline": {"name": "Garuda Indonesia", "iata": "GA", "icao": "GIA"}, "flight": {"number": "165", "iata": "GA165", "icao": "GIA165", "codeshared": null}, "aircraft": null, "live": null}, {"flight_date": "2025-07-05", "flight_status": "scheduled", "departure": {"airport": "Minangkabau International Airport", "timezone": "Asia/Jakarta", "iata": "PDG", "icao": "WIEE", "terminal": null, "gate": null, "delay": null, "scheduled": "2025-07-05T17:35:00+00:00", "estimated": "2025-07-05T17:35:00+00:00", "actual": null, "estimated_runway": null, "actual_runway": null}, "arrival": {"airport": "Soekarno-Hatta International", "timezone": "Asia/Jakarta", "iata": "CGK", "icao": "WIII", "terminal": "3", "gate": null, "baggage": null, "scheduled": "2025-07-05T19:30:00+00:00", "delay": null, "estimated": null, "actual": null, "estimated_runway": null, "actual_runway": null}, "airline": {"name": "Etihad Airways", "iata": "EY", "icao": "ETD"}, "flight": {"number": "7090", "iata": "EY7090", "icao": "ETD7090", "codeshared": {"airline_name": "garuda indonesia", "airline_iata": "ga", "airline_icao": "gia", "flight_number": "165", "flight_iata": "ga165", "flight_icao": "gia165"}}, "aircraft": null, "live": null}, {"flight_date": "2025-07-05", "flight_status": "scheduled", "departure": {"airport": "Minangkabau International Airport", "timezone": "Asia/Jakarta", "iata": "PDG", "icao": "WIEE", "terminal": null, "gate": null, "delay": null, "scheduled": "2025-07-05T17:35:00+00:00", "estimated": "2025-07-05T17:35:00+00:00", "actual": null, "estimated_runway": null, "actual_runway": null}, "arrival": {"airport": "Soekarno-Hatta International", "timezone": "Asia/Jakarta", "iata": "CGK", "icao": "WIII", "terminal": "3", "gate": null, "baggage": null, "scheduled": "2025-07-05T19:30:00+00:00", "delay": null, "estimated": null, "actual": null, "estimated_runway": null, "actual_runway": null}, "airline": {"name": "Japan Airlines", "iata": "JL", "icao": "JTL"}, "flight": {"number": "8480", "iata": "JL8480", "icao": "JTL8480", "codeshared": {"airline_name": "garuda indonesia", "airline_iata": "ga", "airline_icao": "gia", "flight_number": "165", "flight_iata": "ga165", "flight_icao": "gia165"}}, "aircraft": null, "live": null}, {"flight_date": "2025-07-05", "flight_status": "scheduled", "departure": {"airport": "Babullah", "timezone": "Asia/Jayapura", "iata": "TTE", "icao": "WAMT", "terminal": null, "gate": null, "delay": null, "scheduled": "2025-07-05T15:20:00+00:00", "estimated": "2025-07-05T15:20:00+00:00", "actual": null, "estimated_runway": null, "actual_runway": null}, "arrival": {"airport": null, "timezone": null, "iata": "LAH", "icao": "WAPH", "terminal": null, "gate": null, "baggage": null, "scheduled": "2025-07-05T16:05:00+00:00", "delay": null, "estimated": null, "actual": null, "estimated_runway": null, "actual_runway": null}, "airline": {"name": "Wings Air (Indonesia)", "iata": "IW", "icao": "WON"}, "flight": {"number": "1174", "iata": "IW1174", "icao": "WON1174", "codeshared": null}, "aircraft": null, "live": null}, {"flight_date": "2025-07-05", "flight_status": "scheduled", "departure": {"airport": "Xianyang", "timezone": "Asia/Shanghai", "iata": "XIY", "icao": "ZLXY", "terminal": "3", "gate": null, "delay": 26, "scheduled": "2025-07-05T18:45:00+00:00", "estimated": "2025-07-05T18:45:00+00:00", "actual": null, "estimated_runway": null, "actual_runway": null}, "arrival": {"airport": null, "timezone": null, "iata": "HUZ", "icao": "ZGHZ", "terminal": "T2", "gate": null, "baggage": null, "scheduled": "2025-07-05T21:35:00+00:00", "delay": null, "estimated": null, "actual": null, "estimated_runway": null, "actual_runway": null}, "airline": {"name": "Beijing Capital Airlines", "iata": "JD", "icao": "CBJ"}, "flight": {"number": "5283", "iata": "JD5283", "icao": "CBJ5283", "codeshared": null}, "aircraft": null, "live": null}, {"flight_date": "2025-07-05", "flight_status": "scheduled", "departure": {"airport": "Haikou", "timezone": "Asia/Shanghai", "iata": "HAK", "icao": "ZJHK", "terminal": "T1", "gate": null, "delay": null, "scheduled": "2025-07-05T19:25:00+00:00", "estimated": "2025-07-05T19:25:00+00:00", "actual": null, "estimated_runway": null, "actual_runway": null}, "arrival": {"airport": null, "timezone": null, "iata": "HUZ", "icao": "ZGHZ", "terminal": "T2", "gate": null, "baggage": null, "scheduled": "2025-07-05T21:10:00+00:00", "delay": null, "estimated": null, "actual": null, "estimated_runway": null, "actual_runway": null}, "airline": {"name": "Tianjin Airlines", "iata": "GS", "icao": "GCR"}, "flight": {"number": "6531", "iata": "GS6531", "icao": "GCR6531", "codeshared": null}, "aircraft": null, "live": null}, {"flight_date": "2025-07-05", "flight_status": "scheduled", "departure": {"airport": "Guiyang", "timezone": "Asia/Shanghai", "iata": "KWE", "icao": "ZUGY", "terminal": "T3", "gate": null, "delay": null, "scheduled": "2025-07-05T19:00:00+00:00", "estimated": "2025-07-05T19:00:00+00:00", "actual": null, "estimated_runway": null, "actual_runway": null}, "arrival": {"airport": null, "timezone": null, "iata": "HUZ", "icao": "ZGHZ", "terminal": "T2", "gate": null, "baggage": null, "scheduled": "2025-07-05T20:50:00+00:00", "delay": null, "estimated": null, "actual": null, "estimated_runway": null, "actual_runway": null}, "airline": {"name": "Shenzhen Airlines", "iata": "ZH", "icao": "CSZ"}, "flight": {"number": "5053", "iata": "ZH5053", "icao": "CSZ5053", "codeshared": {"airline_name": "juneyao airlines", "airline_iata": "ho", "airline_icao": "dkh", "flight_number": "1902", "flight_iata": "ho1902", "flight_icao": "dkh1902"}}, "aircraft": null, "live": null}, {"flight_date": "2025-07-05", "flight_status": "scheduled", "departure": {"airport": "Guiyang", "timezone": "Asia/Shanghai", "iata": "KWE", "icao": "ZUGY", "terminal": "T3", "gate": null, "delay": null, "scheduled": "2025-07-05T19:00:00+00:00", "estimated": "2025-07-05T19:00:00+00:00", "actual": null, "estimated_runway": null, "actual_runway": null}, "arrival": {"airport": null, "timezone": null, "iata": "HUZ", "icao": "ZGHZ", "terminal": "T2", "gate": null, "baggage": null, "scheduled": "2025-07-05T20:50:00+00:00", "delay": null, "estimated": null, "actual": null, "estimated_runway": null, "actual_runway": null}, "airline": {"name": "China Eastern Airlines", "iata": "MU", "icao": "CES"}, "flight": {"number": "3652", "iata": "MU3652", "icao": "CES3652", "codeshared": {"airline_name": "juneyao airlines", "airline_iata": "ho", "airline_icao": "dkh", "flight_number": "1902", "flight_iata": "ho1902", "flight_icao": "dkh1902"}}, "aircraft": null, "live": null}, {"flight_date": "2025-07-05", "flight_status": "scheduled", "departure": {"airport": "Guiyang", "timezone": "Asia/Shanghai", "iata": "KWE", "icao": "ZUGY", "terminal": "T3", "gate": null, "delay": null, "scheduled": "2025-07-05T19:00:00+00:00", "estimated": "2025-07-05T19:00:00+00:00", "actual": null, "estimated_runway": null, "actual_runway": null}, "arrival": {"airport": null, "timezone": null, "iata": "HUZ", "icao": "ZGHZ", "terminal": "T2", "gate": null, "baggage": null, "scheduled": "2025-07-05T20:50:00+00:00", "delay": null, "estimated": null, "actual": null, "estimated_runway": null, "actual_runway": null}, "airline": {"name": "Xiamen Airlines", "iata": "MF", "icao": "CXA"}, "flight": {"number": "7652", "iata": "MF7652", "icao": "CXA7652", "codeshared": {"airline_name": "juneyao airlines", "airline_iata": "ho", "airline_icao": "dkh", "flight_number": "1902", "flight_iata": "ho1902", "flight_icao": "dkh1902"}}, "aircraft": null, "live": null}, {"flight_date": "2025-07-05", "flight_status": "scheduled", "departure": {"airport": "Guiyang", "timezone": "Asia/Shanghai", "iata": "KWE", "icao": "ZUGY", "terminal": "T3", "gate": null, "delay": null, "scheduled": "2025-07-05T19:00:00+00:00", "estimated": "2025-07-05T19:00:00+00:00", "actual": null, "estimated_runway": null, "actual_runway": null}, "arrival": {"airport": null, "timezone": null, "iata": "HUZ", "icao": "ZGHZ", "terminal": "T2", "gate": null, "baggage": null, "scheduled": "2025-07-05T20:50:00+00:00", "delay": null, "estimated": null, "actual": null, "estimated_runway": null, "actual_runway": null}, "airline": {"name": "China Southern Airlines", "iata": "CZ", "icao": "CSN"}, "flight": {"number": "257", "iata": "CZ257", "icao": "CSN257", "codeshared": {"airline_name": "juneyao airlines", "airline_iata": "ho", "airline_icao": "dkh", "flight_number": "1902", "flight_iata": "ho1902", "flight_icao": "dkh1902"}}, "aircraft": null, "live": null}, {"flight_date": "2025-07-05", "flight_status": "scheduled", "departure": {"airport": "Hangzhou", "timezone": "Asia/Shanghai", "iata": "HGH", "icao": "ZSHC", "terminal": "3", "gate": null, "delay": null, "scheduled": "2025-07-05T18:40:00+00:00", "estimated": "2025-07-05T18:40:00+00:00", "actual": null, "estimated_runway": null, "actual_runway": null}, "arrival": {"airport": null, "timezone": null, "iata": "HUZ", "icao": "ZGHZ", "terminal": "T2", "gate": null, "baggage": null, "scheduled": "2025-07-05T20:40:00+00:00", "delay": null, "estimated": null, "actual": null, "estimated_runway": null, "actual_runway": null}, "airline": {"name": "Juneyao Airlines", "iata": "HO", "icao": "DKH"}, "flight": {"number": "2047", "iata": "HO2047", "icao": "DKH2047", "codeshared": null}, "aircraft": null, "live": null}, {"flight_date": "2025-07-05", "flight_status": "scheduled", "departure": {"airport": "Hangzhou", "timezone": "Asia/Shanghai", "iata": "HGH", "icao": "ZSHC", "terminal": "3", "gate": null, "delay": null, "scheduled": "2025-07-05T18:40:00+00:00", "estimated": "2025-07-05T18:40:00+00:00", "actual": null, "estimated_runway": null, "actual_runway": null}, "arrival": {"airport": null, "timezone": null, "iata": "HUZ", "icao": "ZGHZ", "terminal": "T2", "gate": null, "baggage": null, "scheduled": "2025-07-05T20:40:00+00:00", "delay": null, "estimated": null, "actual": null, "estimated_runway": null, "actual_runway": null}, "airline": {"name": "Shenzhen Airlines", "iata": "ZH", "icao": "CSZ"}, "flight": {"number": "5132", "iata": "ZH5132", "icao": "CSZ5132", "codeshared": {"airline_name": "juneyao airlines", "airline_iata": "ho", "airline_icao": "dkh", "flight_number": "2047", "flight_iata": "ho2047", "flight_icao": "dkh2047"}}, "aircraft": null, "live": null}, {"flight_date": "2025-07-05", "flight_status": "scheduled", "departure": {"airport": "Hangzhou", "timezone": "Asia/Shanghai", "iata": "HGH", "icao": "ZSHC", "terminal": "3", "gate": null, "delay": null, "scheduled": "2025-07-05T18:40:00+00:00", "estimated": "2025-07-05T18:40:00+00:00", "actual": null, "estimated_runway": null, "actual_runway": null}, "arrival": {"airport": null, "timezone": null, "iata": "HUZ", "icao": "ZGHZ", "terminal": "T2", "gate": null, "baggage": null, "scheduled": "2025-07-05T20:40:00+00:00", "delay": null, "estimated": null, "actual": null, "estimated_runway": null, "actual_runway": null}, "airline": {"name": "Sichuan Airlines", "iata": "3U", "icao": "CSC"}, "flight": {"number": "4541", "iata": "3U4541", "icao": "CSC4541", "codeshared": {"airline_name": "juneyao airlines", "airline_iata": "ho", "airline_icao": "dkh", "flight_number": "2047", "flight_iata": "ho2047", "flight_icao": "dkh2047"}}, "aircraft": null, "live": null}, {"flight_date": "2025-07-05", "flight_status": "scheduled", "departure": {"airport": "Hangzhou", "timezone": "Asia/Shanghai", "iata": "HGH", "icao": "ZSHC", "terminal": "3", "gate": null, "delay": null, "scheduled": "2025-07-05T18:40:00+00:00", "estimated": "2025-07-05T18:40:00+00:00", "actual": null, "estimated_runway": null, "actual_runway": null}, "arrival": {"airport": null, "timezone": null, "iata": "HUZ", "icao": "ZGHZ", "terminal": "T2", "gate": null, "baggage": null, "scheduled": "2025-07-05T20:40:00+00:00", "delay": null, "estimated": null, "actual": null, "estimated_runway": null, "actual_runway": null}, "airline": {"name": "China Eastern Airlines", "iata": "MU", "icao": "CES"}, "flight": {"number": "3731", "iata": "MU3731", "icao": "CES3731", "codeshared": {"airline_name": "juneyao airlines", "airline_iata": "ho", "airline_icao": "dkh", "flight_number": "2047", "flight_iata": "ho2047", "flight_icao": "dkh2047"}}, "aircraft": null, "live": null}, {"flight_date": "2025-07-05", "flight_status": "scheduled", "departure": {"airport": "Hangzhou", "timezone": "Asia/Shanghai", "iata": "HGH", "icao": "ZSHC", "terminal": "3", "gate": null, "delay": null, "scheduled": "2025-07-05T18:40:00+00:00", "estimated": "2025-07-05T18:40:00+00:00", "actual": null, "estimated_runway": null, "actual_runway": null}, "arrival": {"airport": null, "timezone": null, "iata": "HUZ", "icao": "ZGHZ", "terminal": "T2", "gate": null, "baggage": null, "scheduled": "2025-07-05T20:40:00+00:00", "delay": null, "estimated": null, "actual": null, "estimated_runway": null, "actual_runway": null}, "airline": {"name": "Xiamen Airlines", "iata": "MF", "icao": "CXA"}, "flight": {"number": "7731", "iata": "MF7731", "icao": "CXA7731", "codeshared": {"airline_name": "juneyao airlines", "airline_iata": "ho", "airline_icao": "dkh", "flight_number": "2047", "flight_iata": "ho2047", "flight_icao": "dkh2047"}}, "aircraft": null, "live": null}, {"flight_date": "2025-07-05", "flight_status": "scheduled", "departure": {"airport": "Hangzhou", "timezone": "Asia/Shanghai", "iata": "HGH", "icao": "ZSHC", "terminal": "3", "gate": null, "delay": null, "scheduled": "2025-07-05T18:40:00+00:00", "estimated": "2025-07-05T18:40:00+00:00", "actual": null, "estimated_runway": null, "actual_runway": null}, "arrival": {"airport": null, "timezone": null, "iata": "HUZ", "icao": "ZGHZ", "terminal": "T2", "gate": null, "baggage": null, "scheduled": "2025-07-05T20:40:00+00:00", "delay": null, "estimated": null, "actual": null, "estimated_runway": null, "actual_runway": null}, "airline": {"name": "China Southern Airlines", "iata": "CZ", "icao": "CSN"}, "flight": {"number": "294", "iata": "CZ294", "icao": "CSN294", "codeshared": {"airline_name": "juneyao airlines", "airline_iata": "ho", "airline_icao": "dkh", "flight_number": "2047", "flight_iata": "ho2047", "flight_icao": "dkh2047"}}, "aircraft": null, "live": null}, {"flight_date": "2025-07-05", "flight_status": "scheduled", "departure": {"airport": "Tianhe International", "timezone": "Asia/Shanghai", "iata": "WUH", "icao": "ZHHH", "terminal": "3", "gate": null, "delay": 35, "scheduled": "2025-07-05T19:15:00+00:00", "estimated": "2025-07-05T19:15:00+00:00", "actual": null, "estimated_runway": null, "actual_runway": null}, "arrival": {"airport": null, "timezone": null, "iata": "HUZ", "icao": "ZGHZ", "terminal": "T2", "gate": null, "baggage": null, "scheduled": "2025-07-05T20:35:00+00:00", "delay": null, "estimated": null, "actual": null, "estimated_runway": null, "actual_runway": null}, "airline": {"name": "Air China LTD", "iata": "CA", "icao": "CCA"}, "flight": {"number": "8257", "iata": "CA8257", "icao": "CCA8257", "codeshared": null}, "aircraft": null, "live": null}, {"flight_date": "2025-07-05", "flight_status": "scheduled", "departure": {"airport": "Tianhe International", "timezone": "Asia/Shanghai", "iata": "WUH", "icao": "ZHHH", "terminal": "3", "gate": null, "delay": 35, "scheduled": "2025-07-05T19:15:00+00:00", "estimated": "2025-07-05T19:15:00+00:00", "actual": null, "estimated_runway": null, "actual_runway": null}, "arrival": {"airport": null, "timezone": null, "iata": "HUZ", "icao": "ZGHZ", "terminal": "T2", "gate": null, "baggage": null, "scheduled": "2025-07-05T20:35:00+00:00", "delay": null, "estimated": null, "actual": null, "estimated_runway": null, "actual_runway": null}, "airline": {"name": "Shenzhen Airlines", "iata": "ZH", "icao": "CSZ"}, "flight": {"number": "1057", "iata": "ZH1057", "icao": "CSZ1057", "codeshared": {"airline_name": "air china ltd", "airline_iata": "ca", "airline_icao": "cca", "flight_number": "8257", "flight_iata": "ca8257", "flight_icao": "cca8257"}}, "aircraft": null, "live": null}, {"flight_date": "2025-07-05", "flight_status": "scheduled", "departure": {"airport": "Tianhe International", "timezone": "Asia/Shanghai", "iata": "WUH", "icao": "ZHHH", "terminal": "3", "gate": null, "delay": 35, "scheduled": "2025-07-05T19:15:00+00:00", "estimated": "2025-07-05T19:15:00+00:00", "actual": null, "estimated_runway": null, "actual_runway": null}, "arrival": {"airport": null, "timezone": null, "iata": "HUZ", "icao": "ZGHZ", "terminal": "T2", "gate": null, "baggage": null, "scheduled": "2025-07-05T20:35:00+00:00", "delay": null, "estimated": null, "actual": null, "estimated_runway": null, "actual_runway": null}, "airline": {"name": "Shandong Airlines", "iata": "SC", "icao": "CDG"}, "flight": {"number": "5735", "iata": "SC5735", "icao": "CDG5735", "codeshared": {"airline_name": "air china ltd", "airline_iata": "ca", "airline_icao": "cca", "flight_number": "8257", "flight_iata": "ca8257", "flight_icao": "cca8257"}}, "aircraft": null, "live": null}, {"flight_date": "2025-07-05", "flight_status": "scheduled", "departure": {"airport": "Chengdu Tianfu International Airport", "timezone": "Asia/Chongqing", "iata": "TFU", "icao": "ZUTF", "terminal": "T2", "gate": null, "delay": null, "scheduled": "2025-07-05T18:05:00+00:00", "estimated": "2025-07-05T18:05:00+00:00", "actual": null, "estimated_runway": null, "actual_runway": null}, "arrival": {"airport": null, "timezone": null, "iata": "HUZ", "icao": "ZGHZ", "terminal": "T2", "gate": null, "baggage": null, "scheduled": "2025-07-05T20:30:00+00:00", "delay": null, "estimated": null, "actual": null, "estimated_runway": null, "actual_runway": null}, "airline": {"name": "China United Airlines", "iata": "KN", "icao": "CUA"}, "flight": {"number": "5119", "iata": "KN5119", "icao": "CUA5119", "codeshared": null}, "aircraft": null, "live": null}, {"flight_date": "2025-07-05", "flight_status": "scheduled", "departure": {"airport": "Chengdu Tianfu International Airport", "timezone": "Asia/Chongqing", "iata": "TFU", "icao": "ZUTF", "terminal": "T2", "gate": null, "delay": null, "scheduled": "2025-07-05T18:05:00+00:00", "estimated": "2025-07-05T18:05:00+00:00", "actual": null, "estimated_runway": null, "actual_runway": null}, "arrival": {"airport": null, "timezone": null, "iata": "HUZ", "icao": "ZGHZ", "terminal": "T2", "gate": null, "baggage": null, "scheduled": "2025-07-05T20:30:00+00:00", "delay": null, "estimated": null, "actual": null, "estimated_runway": null, "actual_runway": null}, "airline": {"name": "China Eastern Airlines", "iata": "MU", "icao": "CES"}, "flight": {"number": "8026", "iata": "MU8026", "icao": "CES8026", "codeshared": {"airline_name": "china united airlines", "airline_iata": "kn", "airline_icao": "cua", "flight_number": "5119", "flight_iata": "kn5119", "flight_icao": "cua5119"}}, "aircraft": null, "live": null}, {"flight_date": "2025-07-05", "flight_status": "scheduled", "departure": {"airport": "Nanchong", "timezone": "Asia/Shanghai", "iata": "NAO", "icao": "ZUNC", "terminal": null, "gate": null, "delay": null, "scheduled": "2025-07-05T17:20:00+00:00", "estimated": "2025-07-05T17:20:00+00:00", "actual": null, "estimated_runway": null, "actual_runway": null}, "arrival": {"airport": null, "timezone": null, "iata": "HUZ", "icao": "ZGHZ", "terminal": "T2", "gate": null, "baggage": null, "scheduled": "2025-07-05T19:50:00+00:00", "delay": null, "estimated": null, "actual": null, "estimated_runway": null, "actual_runway": null}, "airline": {"name": "Chongqing Airlines", "iata": "OQ", "icao": "CQN"}, "flight": {"number": "2210", "iata": "OQ2210", "icao": "CQN2210", "codeshared": null}, "aircraft": null, "live": null}, {"flight_date": "2025-07-05", "flight_status": "scheduled", "departure": {"airport": "Chengdu Tianfu International Airport", "timezone": "Asia/Chongqing", "iata": "TFU", "icao": "ZUTF", "terminal": "2", "gate": "220", "delay": null, "scheduled": "2025-07-05T17:20:00+00:00", "estimated": "2025-07-05T17:20:00+00:00", "actual": null, "estimated_runway": null, "actual_runway": null}, "arrival": {"airport": null, "timezone": null, "iata": "HUZ", "icao": "ZGHZ", "terminal": "T2", "gate": null, "baggage": null, "scheduled": "2025-07-05T19:50:00+00:00", "delay": null, "estimated": null, "actual": null, "estimated_runway": null, "actual_runway": null}, "airline": {"name": "China Eastern Airlines", "iata": "MU", "icao": "CES"}, "flight": {"number": "6137", "iata": "MU6137", "icao": "CES6137", "codeshared": null}, "aircraft": null, "live": null}, {"flight_date": "2025-07-05", "flight_status": "scheduled", "departure": {"airport": "Chengdu Tianfu International Airport", "timezone": "Asia/Chongqing", "iata": "TFU", "icao": "ZUTF", "terminal": "2", "gate": "220", "delay": null, "scheduled": "2025-07-05T17:20:00+00:00", "estimated": "2025-07-05T17:20:00+00:00", "actual": null, "estimated_runway": null, "actual_runway": null}, "arrival": {"airport": null, "timezone": null, "iata": "HUZ", "icao": "ZGHZ", "terminal": "T2", "gate": null, "baggage": null, "scheduled": "2025-07-05T19:50:00+00:00", "delay": null, "estimated": null, "actual": null, "estimated_runway": null, "actual_runway": null}, "airline": {"name": "Sichuan Airlines", "iata": "3U", "icao": "CSC"}, "flight": {"number": "5375", "iata": "3U5375", "icao": "CSC5375", "codeshared": {"airline_name": "china eastern airlines", "airline_iata": "mu", "airline_icao": "ces", "flight_number": "6137", "flight_iata": "mu6137", "flight_icao": "ces6137"}}, "aircraft": null, "live": null}, {"flight_date": "2025-07-05", "flight_status": "scheduled", "departure": {"airport": "Chengdu Tianfu International Airport", "timezone": "Asia/Chongqing", "iata": "TFU", "icao": "ZUTF", "terminal": "2", "gate": "220", "delay": null, "scheduled": "2025-07-05T17:20:00+00:00", "estimated": "2025-07-05T17:20:00+00:00", "actual": null, "estimated_runway": null, "actual_runway": null}, "arrival": {"airport": null, "timezone": null, "iata": "HUZ", "icao": "ZGHZ", "terminal": "T2", "gate": null, "baggage": null, "scheduled": "2025-07-05T19:50:00+00:00", "delay": null, "estimated": null, "actual": null, "estimated_runway": null, "actual_runway": null}, "airline": {"name": "China United Airlines", "iata": "KN", "icao": "CUA"}, "flight": {"number": "6326", "iata": "KN6326", "icao": "CUA6326", "codeshared": {"airline_name": "china eastern airlines", "airline_iata": "mu", "airline_icao": "ces", "flight_number": "6137", "flight_iata": "mu6137", "flight_icao": "ces6137"}}, "aircraft": null, "live": null}, {"flight_date": "2025-07-05", "flight_status": "scheduled", "departure": {"airport": "Chengdu Tianfu International Airport", "timezone": "Asia/Chongqing", "iata": "TFU", "icao": "ZUTF", "terminal": "2", "gate": null, "delay": null, "scheduled": "2025-07-05T17:30:00+00:00", "estimated": "2025-07-05T17:30:00+00:00", "actual": null, "estimated_runway": null, "actual_runway": null}, "arrival": {"airport": null, "timezone": null, "iata": "HUZ", "icao": "ZGHZ", "terminal": "T2", "gate": null, "baggage": null, "scheduled": "2025-07-05T19:50:00+00:00", "delay": null, "estimated": null, "actual": null, "estimated_runway": null, "actual_runway": null}, "airline": {"name": "Air China LTD", "iata": "CA", "icao": "CCA"}, "flight": {"number": "2659", "iata": "CA2659", "icao": "CCA2659", "codeshared": null}, "aircraft": null, "live": null}, {"flight_date": "2025-07-05", "flight_status": "scheduled", "departure": {"airport": "Chengdu Tianfu International Airport", "timezone": "Asia/Chongqing", "iata": "TFU", "icao": "ZUTF", "terminal": "2", "gate": null, "delay": null, "scheduled": "2025-07-05T17:30:00+00:00", "estimated": "2025-07-05T17:30:00+00:00", "actual": null, "estimated_runway": null, "actual_runway": null}, "arrival": {"airport": null, "timezone": null, "iata": "HUZ", "icao": "ZGHZ", "terminal": "T2", "gate": null, "baggage": null, "scheduled": "2025-07-05T19:50:00+00:00", "delay": null, "estimated": null, "actual": null, "estimated_runway": null, "actual_runway": null}, "airline": {"name": "Shenzhen Airlines", "iata": "ZH", "icao": "CSZ"}, "flight": {"number": "4111", "iata": "ZH4111", "icao": "CSZ4111", "codeshared": {"airline_name": "air china ltd", "airline_iata": "ca", "airline_icao": "cca", "flight_number": "2659", "flight_iata": "ca2659", "flight_icao": "cca2659"}}, "aircraft": null, "live": null}, {"flight_date": "2025-07-05", "flight_status": "scheduled", "departure": {"airport": "Tianhe International", "timezone": "Asia/Shanghai", "iata": "WUH", "icao": "ZHHH", "terminal": "3", "gate": "11", "delay": 120, "scheduled": "2025-07-05T17:40:00+00:00", "estimated": "2025-07-05T17:40:00+00:00", "actual": null, "estimated_runway": null, "actual_runway": null}, "arrival": {"airport": null, "timezone": null, "iata": "HUZ", "icao": "ZGHZ", "terminal": "T2", "gate": null, "baggage": null, "scheduled": "2025-07-05T19:25:00+00:00", "delay": null, "estimated": null, "actual": null, "estimated_runway": null, "actual_runway": null}, "airline": {"name": "China Eastern Airlines", "iata": "MU", "icao": "CES"}, "flight": {"number": "2515", "iata": "MU2515", "icao": "CES2515", "codeshared": null}, "aircraft": null, "live": null}, {"flight_date": "2025-07-05", "flight_status": "scheduled", "departure": {"airport": "Xianyang", "timezone": "Asia/Shanghai", "iata": "XIY", "icao": "ZLXY", "terminal": "2", "gate": null, "delay": null, "scheduled": "2025-07-05T16:25:00+00:00", "estimated": "2025-07-05T16:25:00+00:00", "actual": null, "estimated_runway": null, "actual_runway": null}, "arrival": {"airport": null, "timezone": null, "iata": "HUZ", "icao": "ZGHZ", "terminal": "T2", "gate": null, "baggage": null, "scheduled": "2025-07-05T19:20:00+00:00", "delay": null, "estimated": null, "actual": null, "estimated_runway": null, "actual_runway": null}, "airline": {"name": "Shandong Airlines", "iata": "SC", "icao": "CDG"}, "flight": {"number": "9231", "iata": "SC9231", "icao": "CDG9231", "codeshared": {"airline_name": "shenzhen airlines", "airline_iata": "zh", "airline_icao": "csz", "flight_number": "9275", "flight_iata": "zh9275", "flight_icao": "csz9275"}}, "aircraft": null, "live": null}, {"flight_date": "2025-07-05", "flight_status": "scheduled", "departure": {"airport": "Beijing Daxing International Airport", "timezone": "+8", "iata": "PKX", "icao": "ZBAD", "terminal": null, "gate": null, "delay": 6, "scheduled": "2025-07-05T15:40:00+00:00", "estimated": "2025-07-05T15:40:00+00:00", "actual": null, "estimated_runway": null, "actual_runway": null}, "arrival": {"airport": null, "timezone": null, "iata": "HUZ", "icao": "ZGHZ", "terminal": "T2", "gate": null, "baggage": null, "scheduled": "2025-07-05T18:55:00+00:00", "delay": null, "estimated": null, "actual": null, "estimated_runway": null, "actual_runway": null}, "airline": {"name": "China Eastern Airlines", "iata": "MU", "icao": "CES"}, "flight": {"number": "8094", "iata": "MU8094", "icao": "CES8094", "codeshared": {"airline_name": "china united airlines", "airline_iata": "kn", "airline_icao": "cua", "flight_number": "5361", "flight_iata": "kn5361", "flight_icao": "cua5361"}}, "aircraft": null, "live": null}, {"flight_date": "2025-07-05", "flight_status": "scheduled", "departure": {"airport": "Singapore Changi", "timezone": "Asia/Singapore", "iata": "SIN", "icao": "WSSS", "terminal": "1", "gate": "C22", "delay": null, "scheduled": "2025-07-05T16:50:00+00:00", "estimated": "2025-07-05T16:50:00+00:00", "actual": null, "estimated_runway": null, "actual_runway": null}, "arrival": {"airport": "Ngurah Rai International", "timezone": "Asia/Makassar", "iata": "DPS", "icao": "WADD", "terminal": "I", "gate": null, "baggage": "4", "scheduled": "2025-07-05T19:25:00+00:00", "delay": null, "estimated": null, "actual": null, "estimated_runway": null, "actual_runway": null}, "airline": {"name": "Garuda Indonesia", "iata": "GA", "icao": "GIA"}, "flight": {"number": "9000", "iata": "GA9000", "icao": "GIA9000", "codeshared": {"airline_name": "klm", "airline_iata": "kl", "airline_icao": "klm", "flight_number": "835", "flight_iata": "kl835", "flight_icao": "klm835"}}, "aircraft": null, "live": null}, {"flight_date": "2025-07-05", "flight_status": "scheduled", "departure": {"airport": "Singapore Changi", "timezone": "Asia/Singapore", "iata": "SIN", "icao": "WSSS", "terminal": "1", "gate": "C22", "delay": null, "scheduled": "2025-07-05T16:50:00+00:00", "estimated": "2025-07-05T16:50:00+00:00", "actual": null, "estimated_runway": null, "actual_runway": null}, "arrival": {"airport": "Ngurah Rai International", "timezone": "Asia/Makassar", "iata": "DPS", "icao": "WADD", "terminal": "I", "gate": null, "baggage": "4", "scheduled": "2025-07-05T19:25:00+00:00", "delay": null, "estimated": null, "actual": null, "estimated_runway": null, "actual_runway": null}, "airline": {"name": "Air France", "iata": "AF", "icao": "AFR"}, "flight": {"number": "8220", "iata": "AF8220", "icao": "AFR8220", "codeshared": {"airline_name": "klm", "airline_iata": "kl", "airline_icao": "klm", "flight_number": "835", "flight_iata": "kl835", "flight_icao": "klm835"}}, "aircraft": null, "live": null}, {"flight_date": "2025-07-05", "flight_status": "active", "departure": {"airport": "Singapore Changi", "timezone": "Asia/Singapore", "iata": "SIN", "icao": "WSSS", "terminal": "3", "gate": "A14", "delay": null, "scheduled": "2025-07-05T16:40:00+00:00", "estimated": "2025-07-05T16:40:00+00:00", "actual": null, "estimated_runway": null, "actual_runway": null}, "arrival": {"airport": "Beijing Capital International", "timezone": "Asia/Shanghai", "iata": "PEK", "icao": "ZBAA", "terminal": "3", "gate": null, "baggage": "36", "scheduled": "2025-07-05T23:00:00+00:00", "delay": null, "estimated": null, "actual": null, "estimated_runway": null, "actual_runway": null}, "airline": {"name": "Virgin Australia", "iata": "VA", "icao": "VOZ"}, "flight": {"number": "5786", "iata": "VA5786", "icao": "VOZ5786", "codeshared": {"airline_name": "singapore airlines", "airline_iata": "sq", "airline_icao": "sia", "flight_number": "806", "flight_iata": "sq806", "flight_icao": "sia806"}}, "aircraft": null, "live": null}, {"flight_date": "2025-07-05", "flight_status": "active", "departure": {"airport": "Singapore Changi", "timezone": "Asia/Singapore", "iata": "SIN", "icao": "WSSS", "terminal": "3", "gate": "A14", "delay": null, "scheduled": "2025-07-05T16:40:00+00:00", "estimated": "2025-07-05T16:40:00+00:00", "actual": null, "estimated_runway": null, "actual_runway": null}, "arrival": {"airport": "Beijing Capital International", "timezone": "Asia/Shanghai", "iata": "PEK", "icao": "ZBAA", "terminal": "3", "gate": null, "baggage": "36", "scheduled": "2025-07-05T23:00:00+00:00", "delay": null, "estimated": null, "actual": null, "estimated_runway": null, "actual_runway": null}, "airline": {"name": "Ethiopian Airlines", "iata": "ET", "icao": "ETH"}, "flight": {"number": "1340", "iata": "ET1340", "icao": "ETH1340", "codeshared": {"airline_name": "singapore airlines", "airline_iata": "sq", "airline_icao": "sia", "flight_number": "806", "flight_iata": "sq806", "flight_icao": "sia806"}}, "aircraft": null, "live": null}, {"flight_date": "2025-07-05", "flight_status": "active", "departure": {"airport": "Singapore Changi", "timezone": "Asia/Singapore", "iata": "SIN", "icao": "WSSS", "terminal": "3", "gate": "A14", "delay": null, "scheduled": "2025-07-05T16:40:00+00:00", "estimated": "2025-07-05T16:40:00+00:00", "actual": null, "estimated_runway": null, "actual_runway": null}, "arrival": {"airport": "Beijing Capital International", "timezone": "Asia/Shanghai", "iata": "PEK", "icao": "ZBAA", "terminal": "3", "gate": null, "baggage": "36", "scheduled": "2025-07-05T23:00:00+00:00", "delay": null, "estimated": null, "actual": null, "estimated_runway": null, "actual_runway": null}, "airline": {"name": "Air China LTD", "iata": "CA", "icao": "CCA"}, "flight": {"number": "5282", "iata": "CA5282", "icao": "CCA5282", "codeshared": {"airline_name": "singapore airlines", "airline_iata": "sq", "airline_icao": "sia", "flight_number": "806", "flight_iata": "sq806", "flight_icao": "sia806"}}, "aircraft": null, "live": null}, {"flight_date": "2025-07-05", "flight_status": "active", "departure": {"airport": "Singapore Changi", "timezone": "Asia/Singapore", "iata": "SIN", "icao": "WSSS", "terminal": "3", "gate": "B3", "delay": null, "scheduled": "2025-07-05T16:35:00+00:00", "estimated": "2025-07-05T16:35:00+00:00", "actual": null, "estimated_runway": null, "actual_runway": null}, "arrival": {"airport": "Shanghai Pudong International", "timezone": "Asia/Shanghai", "iata": "PVG", "icao": "ZSPD", "terminal": "1", "gate": null, "baggage": "13", "scheduled": "2025-07-05T22:05:00+00:00", "delay": null, "estimated": null, "actual": null, "estimated_runway": null, "actual_runway": null}, "airline": {"name": "Qantas", "iata": "QF", "icao": "QFA"}, "flight": {"number": "4090", "iata": "QF4090", "icao": "QFA4090", "codeshared": {"airline_name": "china eastern airlines", "airline_iata": "mu", "airline_icao": "ces", "flight_number": "568", "flight_iata": "mu568", "flight_icao": "ces568"}}, "aircraft": null, "live": null}, {"flight_date": "2025-07-05", "flight_status": "active", "departure": {"airport": "Singapore Changi", "timezone": "Asia/Singapore", "iata": "SIN", "icao": "WSSS", "terminal": "3", "gate": "B3", "delay": null, "scheduled": "2025-07-05T16:35:00+00:00", "estimated": "2025-07-05T16:35:00+00:00", "actual": null, "estimated_runway": null, "actual_runway": null}, "arrival": {"airport": "Shanghai Pudong International", "timezone": "Asia/Shanghai", "iata": "PVG", "icao": "ZSPD", "terminal": "1", "gate": null, "baggage": "13", "scheduled": "2025-07-05T22:05:00+00:00", "delay": null, "estimated": null, "actual": null, "estimated_runway": null, "actual_runway": null}, "airline": {"name": "Juneyao Airlines", "iata": "HO", "icao": "DKH"}, "flight": {"number": "3512", "iata": "HO3512", "icao": "DKH3512", "codeshared": {"airline_name": "china eastern airlines", "airline_iata": "mu", "airline_icao": "ces", "flight_number": "568", "flight_iata": "mu568", "flight_icao": "ces568"}}, "aircraft": null, "live": null}, {"flight_date": "2025-07-05", "flight_status": "active", "departure": {"airport": "Singapore Changi", "timezone": "Asia/Singapore", "iata": "SIN", "icao": "WSSS", "terminal": "1", "gate": "D36", "delay": null, "scheduled": "2025-07-05T16:35:00+00:00", "estimated": "2025-07-05T16:35:00+00:00", "actual": null, "estimated_runway": null, "actual_runway": null}, "arrival": {"airport": "Duong Dong", "timezone": "Asia/Ho_Chi_Minh", "iata": "PQC", "icao": "VVPQ", "terminal": null, "gate": null, "baggage": null, "scheduled": "2025-07-05T17:20:00+00:00", "delay": null, "estimated": null, "actual": null, "estimated_runway": null, "actual_runway": null}, "airline": {"name": "Singapore Airlines", "iata": "SQ", "icao": "SIA"}, "flight": {"number": "8648", "iata": "SQ8648", "icao": "SIA8648", "codeshared": {"airline_name": "scoot", "airline_iata": "tr", "airline_icao": "tgw", "flight_number": "324", "flight_iata": "tr324", "flight_icao": "tgw324"}}, "aircraft": null, "live": null}, {"flight_date": "2025-07-05", "flight_status": "active", "departure": {"airport": "Singapore Changi", "timezone": "Asia/Singapore", "iata": "SIN", "icao": "WSSS", "terminal": "1", "gate": "D49", "delay": null, "scheduled": "2025-07-05T16:30:00+00:00", "estimated": "2025-07-05T16:30:00+00:00", "actual": null, "estimated_runway": null, "actual_runway": null}, "arrival": {"airport": "Hangzhou", "timezone": "Asia/Shanghai", "iata": "HGH", "icao": "ZSHC", "terminal": "4", "gate": null, "baggage": "29", "scheduled": "2025-07-05T21:35:00+00:00", "delay": null, "estimated": null, "actual": null, "estimated_runway": null, "actual_runway": null}, "airline": {"name": "Singapore Airlines", "iata": "SQ", "icao": "SIA"}, "flight": {"number": "8316", "iata": "SQ8316", "icao": "SIA8316", "codeshared": {"airline_name": "scoot", "airline_iata": "tr", "airline_icao": "tgw", "flight_number": "188", "flight_iata": "tr188", "flight_icao": "tgw188"}}, "aircraft": null, "live": null}, {"flight_date": "2025-07-05", "flight_status": "active", "departure": {"airport": "Singapore Changi", "timezone": "Asia/Singapore", "iata": "SIN", "icao": "WSSS", "terminal": "2", "gate": "E12", "delay": null, "scheduled": "2025-07-05T16:15:00+00:00", "estimated": "2025-07-05T16:15:00+00:00", "actual": null, "estimated_runway": null, "actual_runway": null}, "arrival": {"airport": "Soekarno-Hatta International", "timezone": "Asia/Jakarta", "iata": "CGK", "icao": "WIII", "terminal": "3", "gate": null, "baggage": null, "scheduled": "2025-07-05T17:10:00+00:00", "delay": null, "estimated": null, "actual": null, "estimated_runway": null, "actual_runway": null}, "airline": {"name": "Virgin Australia", "iata": "VA", "icao": "VOZ"}, "flight": {"number": "5834", "iata": "VA5834", "icao": "VOZ5834", "codeshared": {"airline_name": "singapore airlines", "airline_iata": "sq", "airline_icao": "sia", "flight_number": "962", "flight_iata": "sq962", "flight_icao": "sia962"}}, "aircraft": null, "live": null}, {"flight_date": "2025-07-05", "flight_status": "active", "departure": {"airport": "Singapore Changi", "timezone": "Asia/Singapore", "iata": "SIN", "icao": "WSSS", "terminal": "2", "gate": "E12", "delay": null, "scheduled": "2025-07-05T16:15:00+00:00", "estimated": "2025-07-05T16:15:00+00:00", "actual": null, "estimated_runway": null, "actual_runway": null}, "arrival": {"airport": "Soekarno-Hatta International", "timezone": "Asia/Jakarta", "iata": "CGK", "icao": "WIII", "terminal": "3", "gate": null, "baggage": null, "scheduled": "2025-07-05T17:10:00+00:00", "delay": null, "estimated": null, "actual": null, "estimated_runway": null, "actual_runway": null}, "airline": {"name": "SAS", "iata": "SK", "icao": "SAS"}, "flight": {"number": "8085", "iata": "SK8085", "icao": "SAS8085", "codeshared": {"airline_name": "singapore airlines", "airline_iata": "sq", "airline_icao": "sia", "flight_number": "962", "flight_iata": "sq962", "flight_icao": "sia962"}}, "aircraft": null, "live": null}, {"flight_date": "2025-07-05", "flight_status": "active", "departure": {"airport": "Singapore Changi", "timezone": "Asia/Singapore", "iata": "SIN", "icao": "WSSS", "terminal": "2", "gate": "E12", "delay": null, "scheduled": "2025-07-05T16:15:00+00:00", "estimated": "2025-07-05T16:15:00+00:00", "actual": null, "estimated_runway": null, "actual_runway": null}, "arrival": {"airport": "Soekarno-Hatta International", "timezone": "Asia/Jakarta", "iata": "CGK", "icao": "WIII", "terminal": "3", "gate": null, "baggage": null, "scheduled": "2025-07-05T17:10:00+00:00", "delay": null, "estimated": null, "actual": null, "estimated_runway": null, "actual_runway": null}, "airline": {"name": "Garuda Indonesia", "iata": "GA", "icao": "GIA"}, "flight": {"number": "8962", "iata": "GA8962", "icao": "GIA8962", "codeshared": {"airline_name": "singapore airlines", "airline_iata": "sq", "airline_icao": "sia", "flight_number": "962", "flight_iata": "sq962", "flight_icao": "sia962"}}, "aircraft": null, "live": null}, {"flight_date": "2025-07-05", "flight_status": "active", "departure": {"airport": "Singapore Changi", "timezone": "Asia/Singapore", "iata": "SIN", "icao": "WSSS", "terminal": "2", "gate": "E12", "delay": null, "scheduled": "2025-07-05T16:15:00+00:00", "estimated": "2025-07-05T16:15:00+00:00", "actual": null, "estimated_runway": null, "actual_runway": null}, "arrival": {"airport": "Soekarno-Hatta International", "timezone": "Asia/Jakarta", "iata": "CGK", "icao": "WIII", "terminal": "3", "gate": null, "baggage": null, "scheduled": "2025-07-05T17:10:00+00:00", "delay": null, "estimated": null, "actual": null, "estimated_runway": null, "actual_runway": null}, "airline": {"name": "Air India", "iata": "AI", "icao": "AIC"}, "flight": {"number": "8130", "iata": "AI8130", "icao": "AIC8130", "codeshared": {"airline_name": "singapore airlines", "airline_iata": "sq", "airline_icao": "sia", "flight_number": "962", "flight_iata": "sq962", "flight_icao": "sia962"}}, "aircraft": null, "live": null}, {"flight_date": "2025-07-05", "flight_status": "active", "departure": {"airport": "Singapore Changi", "timezone": "Asia/Singapore", "iata": "SIN", "icao": "WSSS", "terminal": "2", "gate": "E6", "delay": null, "scheduled": "2025-07-05T16:15:00+00:00", "estimated": "2025-07-05T16:15:00+00:00", "actual": null, "estimated_runway": null, "actual_runway": null}, "arrival": {"airport": "Phuket International", "timezone": "Asia/Bangkok", "iata": "HKT", "icao": "VTSP", "terminal": "I", "gate": null, "baggage": "2", "scheduled": "2025-07-05T17:10:00+00:00", "delay": null, "estimated": null, "actual": null, "estimated_runway": null, "actual_runway": null}, "airline": {"name": "Virgin Australia", "iata": "VA", "icao": "VOZ"}, "flight": {"number": "5736", "iata": "VA5736", "icao": "VOZ5736", "codeshared": {"airline_name": "singapore airlines", "airline_iata": "sq", "airline_icao": "sia", "flight_number": "736", "flight_iata": "sq736", "flight_icao": "sia736"}}, "aircraft": null, "live": null}, {"flight_date": "2025-07-05", "flight_status": "active", "departure": {"airport": "Singapore Changi", "timezone": "Asia/Singapore", "iata": "SIN", "icao": "WSSS", "terminal": "2", "gate": "E6", "delay": null, "scheduled": "2025-07-05T16:15:00+00:00", "estimated": "2025-07-05T16:15:00+00:00", "actual": null, "estimated_runway": null, "actual_runway": null}, "arrival": {"airport": "Phuket International", "timezone": "Asia/Bangkok", "iata": "HKT", "icao": "VTSP", "terminal": "I", "gate": null, "baggage": "2", "scheduled": "2025-07-05T17:10:00+00:00", "delay": null, "estimated": null, "actual": null, "estimated_runway": null, "actual_runway": null}, "airline": {"name": "Bangkok Airways", "iata": "PG", "icao": "BKP"}, "flight": {"number": "4722", "iata": "PG4722", "icao": "BKP4722", "codeshared": {"airline_name": "singapore airlines", "airline_iata": "sq", "airline_icao": "sia", "flight_number": "736", "flight_iata": "sq736", "flight_icao": "sia736"}}, "aircraft": null, "live": null}, {"flight_date": "2025-07-05", "flight_status": "active", "departure": {"airport": "Singapore Changi", "timezone": "Asia/Singapore", "iata": "SIN", "icao": "WSSS", "terminal": "2", "gate": "E6", "delay": null, "scheduled": "2025-07-05T16:15:00+00:00", "estimated": "2025-07-05T16:15:00+00:00", "actual": null, "estimated_runway": null, "actual_runway": null}, "arrival": {"airport": "Phuket International", "timezone": "Asia/Bangkok", "iata": "HKT", "icao": "VTSP", "terminal": "I", "gate": null, "baggage": "2", "scheduled": "2025-07-05T17:10:00+00:00", "delay": null, "estimated": null, "actual": null, "estimated_runway": null, "actual_runway": null}, "airline": {"name": "Air New Zealand", "iata": "NZ", "icao": "ANZ"}, "flight": {"number": "3496", "iata": "NZ3496", "icao": "ANZ3496", "codeshared": {"airline_name": "singapore airlines", "airline_iata": "sq", "airline_icao": "sia", "flight_number": "736", "flight_iata": "sq736", "flight_icao": "sia736"}}, "aircraft": null, "live": null}, {"flight_date": "2025-07-05", "flight_status": "active", "departure": {"airport": "Singapore Changi", "timezone": "Asia/Singapore", "iata": "SIN", "icao": "WSSS", "terminal": "3", "gate": "A19", "delay": null, "scheduled": "2025-07-05T16:15:00+00:00", "estimated": "2025-07-05T16:15:00+00:00", "actual": null, "estimated_runway": null, "actual_runway": null}, "arrival": {"airport": "Soekarno-Hatta International", "timezone": "Asia/Jakarta", "iata": "CGK", "icao": "WIII", "terminal": "2", "gate": null, "baggage": null, "scheduled": "2025-07-05T17:10:00+00:00", "delay": null, "estimated": null, "actual": null, "estimated_runway": null, "actual_runway": null}, "airline": {"name": "Malindo Air", "iata": "OD", "icao": "MXD"}, "flight": {"number": "9113", "iata": "OD9113", "icao": "MXD9113", "codeshared": {"airline_name": "batik air", "airline_iata": "id", "airline_icao": "btk", "flight_number": "7150", "flight_iata": "id7150", "flight_icao": "btk7150"}}, "aircraft": null, "live": null}, {"flight_date": "2025-07-05", "flight_status": "active", "departure": {"airport": "Singapore Changi", "timezone": "Asia/Singapore", "iata": "SIN", "icao": "WSSS", "terminal": "2", "gate": "E26", "delay": null, "scheduled": "2025-07-05T16:10:00+00:00", "estimated": "2025-07-05T16:10:00+00:00", "actual": null, "estimated_runway": null, "actual_runway": null}, "arrival": {"airport": "Ngurah Rai International", "timezone": "Asia/Makassar", "iata": "DPS", "icao": "WADD", "terminal": "I", "gate": null, "baggage": "2", "scheduled": "2025-07-05T18:50:00+00:00", "delay": null, "estimated": null, "actual": null, "estimated_runway": null, "actual_runway": null}, "airline": {"name": "United Airlines", "iata": "UA", "icao": "UAL"}, "flight": {"number": "7702", "iata": "UA7702", "icao": "UAL7702", "codeshared": {"airline_name": "singapore airlines", "airline_iata": "sq", "airline_icao": "sia", "flight_number": "944", "flight_iata": "sq944", "flight_icao": "sia944"}}, "aircraft": null, "live": null}, {"flight_date": "2025-07-05", "flight_status": "active", "departure": {"airport": "Singapore Changi", "timezone": "Asia/Singapore", "iata": "SIN", "icao": "WSSS", "terminal": "2", "gate": "E26", "delay": null, "scheduled": "2025-07-05T16:10:00+00:00", "estimated": "2025-07-05T16:10:00+00:00", "actual": null, "estimated_runway": null, "actual_runway": null}, "arrival": {"airport": "Ngurah Rai International", "timezone": "Asia/Makassar", "iata": "DPS", "icao": "WADD", "terminal": "I", "gate": null, "baggage": "2", "scheduled": "2025-07-05T18:50:00+00:00", "delay": null, "estimated": null, "actual": null, "estimated_runway": null, "actual_runway": null}, "airline": {"name": "SAS", "iata": "SK", "icao": "SAS"}, "flight": {"number": "8089", "iata": "SK8089", "icao": "SAS8089", "codeshared": {"airline_name": "singapore airlines", "airline_iata": "sq", "airline_icao": "sia", "flight_number": "944", "flight_iata": "sq944", "flight_icao": "sia944"}}, "aircraft": null, "live": null}, {"flight_date": "2025-07-05", "flight_status": "active", "departure": {"airport": "Singapore Changi", "timezone": "Asia/Singapore", "iata": "SIN", "icao": "WSSS", "terminal": "2", "gate": "E26", "delay": null, "scheduled": "2025-07-05T16:10:00+00:00", "estimated": "2025-07-05T16:10:00+00:00", "actual": null, "estimated_runway": null, "actual_runway": null}, "arrival": {"airport": "Ngurah Rai International", "timezone": "Asia/Makassar", "iata": "DPS", "icao": "WADD", "terminal": "I", "gate": null, "baggage": "2", "scheduled": "2025-07-05T18:50:00+00:00", "delay": null, "estimated": null, "actual": null, "estimated_runway": null, "actual_runway": null}, "airline": {"name": "Garuda Indonesia", "iata": "GA", "icao": "GIA"}, "flight": {"number": "9072", "iata": "GA9072", "icao": "GIA9072", "codeshared": {"airline_name": "singapore airlines", "airline_iata": "sq", "airline_icao": "sia", "flight_number": "944", "flight_iata": "sq944", "flight_icao": "sia944"}}, "aircraft": null, "live": null}, {"flight_date": "2025-07-05", "flight_status": "active", "departure": {"airport": "Singapore Changi", "timezone": "Asia/Singapore", "iata": "SIN", "icao": "WSSS", "terminal": "2", "gate": "E26", "delay": null, "scheduled": "2025-07-05T16:10:00+00:00", "estimated": "2025-07-05T16:10:00+00:00", "actual": null, "estimated_runway": null, "actual_runway": null}, "arrival": {"airport": "Ngurah Rai International", "timezone": "Asia/Makassar", "iata": "DPS", "icao": "WADD", "terminal": "I", "gate": null, "baggage": "2", "scheduled": "2025-07-05T18:50:00+00:00", "delay": null, "estimated": null, "actual": null, "estimated_runway": null, "actual_runway": null}, "airline": {"name": "Air India", "iata": "AI", "icao": "AIC"}, "flight": {"number": "8148", "iata": "AI8148", "icao": "AIC8148", "codeshared": {"airline_name": "singapore airlines", "airline_iata": "sq", "airline_icao": "sia", "flight_number": "944", "flight_iata": "sq944", "flight_icao": "sia944"}}, "aircraft": null, "live": null}, {"flight_date": "2025-07-05", "flight_status": "active", "departure": {"airport": "Singapore Changi", "timezone": "Asia/Singapore", "iata": "SIN", "icao": "WSSS", "terminal": "1", "gate": "D44", "delay": null, "scheduled": "2025-07-05T16:05:00+00:00", "estimated": "2025-07-05T16:05:00+00:00", "actual": null, "estimated_runway": null, "actual_runway": null}, "arrival": {"airport": "King Abdulaziz International", "timezone": "Asia/Riyadh", "iata": "JED", "icao": "OEJN", "terminal": "1", "gate": null, "baggage": null, "scheduled": "2025-07-05T20:35:00+00:00", "delay": null, "estimated": null, "actual": null, "estimated_runway": null, "actual_runway": null}, "airline": {"name": "Singapore Airlines", "iata": "SQ", "icao": "SIA"}, "flight": {"number": "8328", "iata": "SQ8328", "icao": "SIA8328", "codeshared": {"airline_name": "scoot", "airline_iata": "tr", "airline_icao": "tgw", "flight_number": "596", "flight_iata": "tr596", "flight_icao": "tgw596"}}, "aircraft": null, "live": null}]}